[
  {"type":"header","version":"4.7.4","comment":"Export to JSON plugin for PHPMyAdmin"},
  {"type":"database","name":"mobilehome"},
  {"type":"table","name":"campus","database":"mobilehome","data":
    [
      {"id":"1","name":"\u653f\u6cbb\u5927\u5b78","school_id":"1","county_id":"1","place_id":"ChIJSS8sRXmqQjQRB_U7jlAHjZ4","latitude":"24.987516","longitude":"121.576074"},
      {"id":"2","name":"\u6e05\u83ef\u5927\u5b78","school_id":"2","county_id":"5","place_id":"ChIJB7ZNzXI2aDQREwR22ltdKxE","latitude":"24.7947253","longitude":"120.9932316"},
      {"id":"3","name":"\u53f0\u7063\u5927\u5b78","school_id":"3","county_id":"1","place_id":"ChIJqS4y_ompQjQRZn8d7gQEdSE","latitude":"25.0173405","longitude":"121.5397518"},
      {"id":"4","name":"\u53f0\u7063\u5e2b\u7bc4\u5927\u5b78","school_id":"4","county_id":"1","place_id":"ChIJYb4lRIWpQjQRNAav7O-Ymcc","latitude":"25.0260598","longitude":"121.5275321"},
      {"id":"5","name":"\u53f0\u7063\u5e2b\u7bc4\u5927\u5b78\u516c\u9928\u6821\u5340","school_id":"4","county_id":"1","place_id":"ChIJi3OrJx6qQjQRdTRYN4zjWy4","latitude":"25.0081215","longitude":"121.5359759"},
      {"id":"6","name":"\u6210\u529f\u5927\u5b78","school_id":"5","county_id":"15","place_id":"ChIJ0yAIKe12bjQRnqEH4osC7uA","latitude":"22.9996873","longitude":"120.2180947"},
      {"id":"7","name":"\u4e2d\u8208\u5927\u5b78","school_id":"6","county_id":"9","place_id":"ChIJ2en_7Pw8aTQROiCtDdz6iuI","latitude":"24.123552","longitude":"120.675326"},
      {"id":"8","name":"\u4ea4\u901a\u5927\u5b78","school_id":"7","county_id":"5","place_id":"ChIJq6pqEBA2aDQRJCbo-x0MeCE","latitude":"24.7859852","longitude":"120.9999097"},
      {"id":"9","name":"\u4ea4\u901a\u5927\u5b78\u535a\u611b\u6821\u5340","school_id":"7","county_id":"5","place_id":"ChIJixrR5xE2aDQRVqwkbRHKwAU","latitude":"24.7975354","longitude":"120.9819094"},
      {"id":"10","name":"\u4ea4\u901a\u5927\u5b78\u53f0\u5317\u6821\u5340","school_id":"7","county_id":"5","place_id":"ChIJkXM8BA2pQjQRMECp0cQHwyU","latitude":"25.0473007","longitude":"121.5118674"},
      {"id":"11","name":"\u4e2d\u592e\u5927\u5b78","school_id":"8","county_id":"7","place_id":"ChIJy02Q7MEjaDQRVuRcRdQpwc0","latitude":"24.9694808","longitude":"121.1925163"},
      {"id":"12","name":"\u4e2d\u5c71\u5927\u5b78","school_id":"9","county_id":"16","place_id":"ChIJdXYFVA8EbjQRCLqM-tdul98","latitude":"22.6264249","longitude":"120.265843"},
      {"id":"13","name":"\u53f0\u7063\u6d77\u6d0b\u5927\u5b78","school_id":"10","county_id":"2","place_id":"ChIJc_BEPAZPXTQRTcHcdR-hjQU","latitude":"25.1508552","longitude":"121.7726863"},
      {"id":"14","name":"\u4e2d\u6b63\u5927\u5b78","school_id":"11","county_id":"13","place_id":"ChIJR3gH11a-bjQRpBDRPsB8qR4","latitude":"23.5633761","longitude":"120.4728831"},
      {"id":"15","name":"\u9ad8\u96c4\u5e2b\u7bc4\u5927\u5b78\u548c\u5e73\u6821\u5340","school_id":"12","county_id":"16","place_id":"ChIJ9R_Vfr0EbjQRtfbCIeHEQ9M","latitude":"22.6259594","longitude":"120.3208026"},
      {"id":"16","name":"\u9ad8\u96c4\u5e2b\u7bc4\u5927\u5b78\u71d5\u5de2\u6821\u5340","school_id":"12","county_id":"16","place_id":"ChIJ47i0GscTbjQRN8rQHU4uGdU","latitude":"22.7868514","longitude":"120.405332"},
      {"id":"17","name":"\u5f70\u5316\u5e2b\u7bc4\u5927\u5b78\u9032\u5fb7\u6821\u5340","school_id":"13","county_id":"10","place_id":"ChIJ3aUyw-k4aTQRzKDmptuN0H8","latitude":"24.082772","longitude":"120.5586279"},
      {"id":"18","name":"\u967d\u660e\u5927\u5b78","school_id":"14","county_id":"1","place_id":"ChIJF6MYcmCuQjQRV4-Sv3dD514","latitude":"25.123002","longitude":"121.513702"},
      {"id":"19","name":"\u53f0\u5317\u5927\u5b78\u4e09\u5cfd\u6821\u5340","school_id":"15","county_id":"3","place_id":"ChIJX_W9agocaDQRgQPshErHNYI","latitude":"24.9452171","longitude":"121.3727153"},
      {"id":"20","name":"\u53f0\u5317\u5927\u5b78\u53f0\u5317\u6821\u5340","school_id":"15","county_id":"3","place_id":"ChIJqw5o_eOrQjQRdjVZ6Yr0ACA","latitude":"25.058174","longitude":"121.542089"},
      {"id":"21","name":"\u5609\u7fa9\u5927\u5b78","school_id":"16","county_id":"12","place_id":"ChIJqWePmViUbjQReE2e45PXiIs","latitude":"23.4687991","longitude":"120.4851352"},
      {"id":"22","name":"\u5609\u7fa9\u5927\u5b78\u65b0\u6c11\u6821\u5340","school_id":"16","county_id":"12","place_id":"ChIJr5uO5xiUbjQRA_-dGJ-YouE","latitude":"23.4637468","longitude":"120.4427052"},
      {"id":"23","name":"\u5609\u7fa9\u5927\u5b78\u6c11\u96c4\u6821\u5340","school_id":"16","county_id":"13","place_id":"ChIJ1-CK6Pq9bjQR8wf7y4Rh9nw","latitude":"23.5436443","longitude":"120.4233654"},
      {"id":"24","name":"\u5609\u7fa9\u5927\u5b78\u6797\u68ee\u6821\u5340","school_id":"16","county_id":"12","place_id":"ChIJOdOkjbWVbjQRq08W-9vvORI","latitude":"23.4882996","longitude":"120.4587608"},
      {"id":"25","name":"\u9ad8\u96c4\u5927\u5b78","school_id":"17","county_id":"16","place_id":"ChIJO9VRShEPbjQR8lX-r-yB5uY","latitude":"22.7340878","longitude":"120.2836491"},
      {"id":"26","name":"\u6771\u83ef\u5927\u5b78","school_id":"18","county_id":"20","place_id":"ChIJWwqDLVehaDQR2OAptx_4hkc","latitude":"23.8976625","longitude":"121.541773"},
      {"id":"27","name":"\u66a8\u5357\u570b\u969b\u5927\u5b78","school_id":"19","county_id":"11","place_id":"ChIJc667hiPYaDQRrr1Wr2xLEPg","latitude":"23.9510746","longitude":"120.9312595"},
      {"id":"28","name":"\u53f0\u7063\u79d1\u6280\u5927\u5b78","school_id":"20","county_id":"1","place_id":"ChIJrcDEdiGqQjQRVfQp7kRe25A","latitude":"25.0136906","longitude":"121.5406792"},
      {"id":"29","name":"\u96f2\u6797\u79d1\u6280\u5927\u5b78","school_id":"21","county_id":"14","place_id":"ChIJW2F5wATIbjQRvlQ5mFnYGd8","latitude":"23.6960596","longitude":"120.5340433"},
      {"id":"30","name":"\u5c4f\u6771\u79d1\u6280\u5927\u5b78","school_id":"22","county_id":"18","place_id":"ChIJe4DLp7U8bjQR854BeSCy2n8","latitude":"22.644444","longitude":"120.609764"},
      {"id":"31","name":"\u53f0\u5317\u79d1\u6280\u5927\u5b78","school_id":"23","county_id":"1","place_id":"ChIJ35hVJX2pQjQRqlM_j4506kc","latitude":"25.0422329","longitude":"121.5354974"},
      {"id":"32","name":"\u9ad8\u96c4\u7b2c\u4e00\u79d1\u6280\u5927\u5b78","school_id":"24","county_id":"16","place_id":"ChIJYfXWVSMObjQRCPdrJRQ7Iks","latitude":"22.7544845","longitude":"120.332831"},
      {"id":"33","name":"\u9ad8\u96c4\u61c9\u7528\u79d1\u6280\u5927\u5b78\u5efa\u5de5\u6821\u5340","school_id":"25","county_id":"16","place_id":"ChIJkWoJHdkEbjQRVjx5fH9-znU","latitude":"22.6517982","longitude":"120.3286736"},
      {"id":"34","name":"\u53f0\u5317\u85dd\u8853\u5927\u5b78","school_id":"26","county_id":"1","place_id":"ChIJQ6iJ4HSvQjQRKv7lAp2njNs","latitude":"25.1325182","longitude":"121.4696818"},
      {"id":"35","name":"\u53f0\u7063\u85dd\u8853\u5927\u5b78","school_id":"27","county_id":"3","place_id":"ChIJkfQrh6sCaDQRorUVxggmikM","latitude":"25.0059234","longitude":"121.4476411"},
      {"id":"36","name":"\u53f0\u6771\u5927\u5b78","school_id":"28","county_id":"19","place_id":"ChIJN1xdb0e5bzQRYjatTCAfpTk","latitude":"22.736571","longitude":"121.067897"},
      {"id":"37","name":"\u5b9c\u862d\u5927\u5b78","school_id":"29","county_id":"4","place_id":"ChIJXUOeb-nkZzQR2OB63tWzg34","latitude":"24.7462695","longitude":"121.7489071"},
      {"id":"38","name":"\u806f\u5408\u5927\u5b78","school_id":"30","county_id":"8","place_id":"ChIJm5eOLeSraTQR-K8xwbEyY8E","latitude":"24.5458044","longitude":"120.81232"},
      {"id":"39","name":"\u864e\u5c3e\u79d1\u6280\u5927\u5b78","school_id":"31","county_id":"14","place_id":"ChIJES_iLge6bjQR1wdykAXtilU","latitude":"23.7031081","longitude":"120.4301509"},
      {"id":"40","name":"\u9ad8\u96c4\u6d77\u6d0b\u79d1\u6280\u5927\u5b78\u6960\u6893\u6821\u5340","school_id":"32","county_id":"16","place_id":"ChIJCXPY-7sPbjQRAWDvRngDIe0","latitude":"22.7246559","longitude":"120.3146027"},
      {"id":"41","name":"\u9ad8\u96c4\u6d77\u6d0b\u79d1\u6280\u5927\u5b78\u65d7\u6d25\u6821\u5340","school_id":"32","county_id":"16","place_id":"ChIJ6c-Q3-wDbjQRmOtSFE6kGcg","latitude":"22.6088275","longitude":"120.2720962"},
      {"id":"42","name":"\u53f0\u5357\u85dd\u8853\u5927\u5b78","school_id":"33","county_id":"15","place_id":"ChIJ0a4HYZFibjQR4BAOVczxlxw","latitude":"23.186013","longitude":"120.374319"},
      {"id":"43","name":"\u53f0\u5357\u5927\u5b78","school_id":"34","county_id":"15","place_id":"ChIJq3vQKIF2bjQR5LbMsTdKguU","latitude":"22.9847814","longitude":"120.2079978"},
      {"id":"44","name":"\u53f0\u5317\u6559\u80b2\u5927\u5b78","school_id":"35","county_id":"1","place_id":"ChIJESYjqAipQjQRxyVQGteyv-4","latitude":"25.023387","longitude":"121.5453446"},
      {"id":"45","name":"\u6e05\u83ef\u5927\u5b78","school_id":"36","county_id":"5","place_id":"ChIJmecsSO01aDQRGT_QzrFSwfA","latitude":"24.7944654","longitude":"120.9652304"},
      {"id":"46","name":"\u53f0\u4e2d\u6559\u80b2\u5927\u5b78","school_id":"37","county_id":"9","place_id":"ChIJewhPQgs9aTQR_DF9suIkJDQ","latitude":"24.1424176","longitude":"120.6721366"},
      {"id":"47","name":"\u6f8e\u6e56\u79d1\u6280\u5927\u5b78","school_id":"38","county_id":"17","place_id":"ChIJ3ywFg91abDQRh6cn77npPBk","latitude":"23.575495","longitude":"119.580949"},
      {"id":"48","name":"\u52e4\u76ca\u79d1\u6280\u5927\u5b78","school_id":"39","county_id":"9","place_id":"ChIJiXopb6MiaTQR3Kqck17fNSQ","latitude":"24.1463428","longitude":"120.7331112"},
      {"id":"49","name":"\u9ad4\u80b2\u5927\u5b78","school_id":"40","county_id":"7","place_id":"ChIJHcpttWWnQjQRAXdBYSK0CZc","latitude":"25.0320129","longitude":"121.3866759"},
      {"id":"50","name":"\u53f0\u5317\u8b77\u7406\u5065\u5eb7\u5927\u5b78\u6821\u672c\u90e8","school_id":"41","county_id":"1","place_id":"ChIJebxOxYuuQjQReLCXnmWdKv0","latitude":"25.1178477","longitude":"121.5199001"},
      {"id":"51","name":"\u53f0\u5317\u8b77\u7406\u5065\u5eb7\u5927\u5b78\u57ce\u5340\u90e8","school_id":"41","county_id":"1","place_id":"ChIJtw4OEgipQjQRUUJqkCuE2bw","latitude":"25.0419761","longitude":"121.5032197"},
      {"id":"52","name":"\u53f0\u5317\u8b77\u7406\u5065\u5eb7\u5927\u5b78\u79d1\u6280\u5927\u6a13","school_id":"41","county_id":"1","place_id":"ChIJJZjiZ4muQjQR9tvjepuSSqc","latitude":"25.117523","longitude":"121.5206632"},
      {"id":"53","name":"\u9ad8\u96c4\u9910\u65c5\u5927\u5b78","school_id":"42","county_id":"16","place_id":"ChIJAUcLkOYcbjQR3EH5niS-EO0","latitude":"22.5632539","longitude":"120.3723822"},
      {"id":"54","name":"\u91d1\u9580\u5927\u5b78","school_id":"43","county_id":"21","place_id":"ChIJb-VnmV-iFDQRpot-C6WTwPE","latitude":"24.4481458","longitude":"118.3225393"},
      {"id":"55","name":"\u53f0\u7063\u9ad4\u80b2\u904b\u52d5\u5927\u5b78","school_id":"44","county_id":"9","place_id":"ChIJ05cc-2c9aTQR_-_82hLFhBk","latitude":"24.1516372","longitude":"120.6888596"},
      {"id":"56","name":"\u53f0\u4e2d\u79d1\u6280\u5927\u5b78","school_id":"45","county_id":"9","place_id":"ChIJ6UcMz2g9aTQR93W4RaBGbj0","latitude":"24.1504536","longitude":"120.6832528"},
      {"id":"57","name":"\u53f0\u5317\u5546\u696d\u5927\u5b78","school_id":"46","county_id":"1","place_id":"ChIJrYQaoXCpQjQRlyCBKCVf4Fg","latitude":"25.0418563","longitude":"121.5256438"},
      {"id":"58","name":"\u5c4f\u6771\u5927\u5b78\u6c11\u751f\u6821\u5340","school_id":"47","county_id":"18","place_id":"ChIJKXoLrowXbjQRcwpacOFZv1A","latitude":"22.6642416","longitude":"120.5038184"},
      {"id":"59","name":"\u5c4f\u6771\u5927\u5b78\u5c4f\u5546\u6821\u5340","school_id":"47","county_id":"18","place_id":"ChIJTwCjux0YbjQRMIr91mQm1GI","latitude":"22.659451","longitude":"120.5116189"},
      {"id":"60","name":"\u53f0\u7063\u6232\u66f2\u5b78\u9662\u5167\u6e56\u6821\u5340","school_id":"48","county_id":"1","place_id":"ChIJ6bpYmIusQjQRfruvQAJtZ3g","latitude":"25.0821882","longitude":"121.5865591"},
      {"id":"61","name":"\u7a7a\u4e2d\u5927\u5b78","school_id":"49","county_id":"3","place_id":"ChIJnYcH8bWoQjQREJMr5B82a8w","latitude":"25.0870514","longitude":"121.4687093"},
      {"id":"62","name":"\u6771\u6d77\u5927\u5b78","school_id":"50","county_id":"9","place_id":"ChIJB2dAOhw-aTQRaoCyT7wBPdQ","latitude":"24.1815869","longitude":"120.603122"},
      {"id":"63","name":"\u8f14\u4ec1\u5927\u5b78","school_id":"51","county_id":"3","place_id":"ChIJDSNgn8KnQjQRPcD80cC8sZw","latitude":"25.0354303","longitude":"121.4324641"},
      {"id":"64","name":"\u6771\u5433\u5927\u5b78\u5916\u96d9\u6eaa\u6821\u5340","school_id":"52","county_id":"1","place_id":"ChIJDTRwjyKsQjQRb1xIYPlyAJo","latitude":"25.0952273","longitude":"121.5457421"},
      {"id":"65","name":"\u6771\u5433\u5927\u5b78\u63a8\u5ee3\u90e8","school_id":"52","county_id":"1","place_id":"ChIJlwxryKCpQjQRT9X_fK9fvsY","latitude":"25.038924","longitude":"121.509998"},
      {"id":"66","name":"\u4e2d\u539f\u5927\u5b78","school_id":"53","county_id":"7","place_id":"ChIJIfCgRxQiaDQR_7y4C2XShis","latitude":"24.957537","longitude":"121.2410215"},
      {"id":"67","name":"\u6de1\u6c5f\u5927\u5b78","school_id":"54","county_id":"3","place_id":"ChIJ20tUwfivQjQRKzazlPT03AE","latitude":"25.1753389","longitude":"121.4500026"},
      {"id":"68","name":"\u4e2d\u570b\u6587\u5316\u5927\u5b78","school_id":"55","county_id":"1","place_id":"ChIJBzv6Mt6tQjQRW3WOPKo5qD8","latitude":"25.135448","longitude":"121.5399074"},
      {"id":"69","name":"\u9022\u7532\u5927\u5b78","school_id":"56","county_id":"9","place_id":"ChIJp4qYpyMWaTQRWgPDQWwU3XM","latitude":"24.178816","longitude":"120.646705"},
      {"id":"70","name":"\u975c\u5b9c\u5927\u5b78","school_id":"57","county_id":"9","place_id":"ChIJz3rQP6sVaTQRo1R6CWdJ6os","latitude":"24.2267756","longitude":"120.5793531"},
      {"id":"71","name":"\u9577\u5e9a\u5927\u5b78","school_id":"58","county_id":"7","place_id":"ChIJIR_3XnunQjQRSAjRIIToS5I","latitude":"25.0307388","longitude":"121.3896892"},
      {"id":"72","name":"\u5143\u667a\u5927\u5b78","school_id":"59","county_id":"7","place_id":"ChIJzT_UkFQfaDQRKzMr5ae1bhg","latitude":"24.9701632","longitude":"121.2674614"},
      {"id":"73","name":"\u4e2d\u83ef\u5927\u5b78","school_id":"60","county_id":"5","place_id":"ChIJ_SIGtlxKaDQR27CXjAjV6rA","latitude":"24.7571075","longitude":"120.952429"},
      {"id":"74","name":"\u5927\u8449\u5927\u5b78","school_id":"61","county_id":"10","place_id":"ChIJ9XYhyVw3aTQR1kN0HlJASWU","latitude":"24.000073","longitude":"120.596098"},
      {"id":"75","name":"\u83ef\u68b5\u5927\u5b78","school_id":"62","county_id":"3","place_id":"ChIJg8-pVblVXTQRxky94OeTycE","latitude":"24.980779","longitude":"121.692123"},
      {"id":"76","name":"\u7fa9\u5b88\u5927\u5b78","school_id":"63","county_id":"16","place_id":"ChIJaSY3OxwRbjQR3Pw2sn-fs0g","latitude":"22.7271723","longitude":"120.4058219"},
      {"id":"77","name":"\u7fa9\u5b88\u5927\u5b78\u91ab\u5b78\u9662","school_id":"63","county_id":"16","place_id":"ChIJSTFZ7u0RbjQRXiXERuR-HFo","latitude":"22.763548","longitude":"120.362515"},
      {"id":"78","name":"\u4e16\u65b0\u5927\u5b78","school_id":"64","county_id":"1","place_id":"ChIJm_VJcgeqQjQRVPNIc_1gWPs","latitude":"24.988664","longitude":"121.543984"},
      {"id":"79","name":"\u9298\u50b3\u5927\u5b78\u53f0\u5317\u6821\u5340","school_id":"65","county_id":"1","place_id":"ChIJo6b-gLCuQjQR5Xb-_ZBB29E","latitude":"25.087255","longitude":"121.5269672"},
      {"id":"80","name":"\u5be6\u8e10\u5927\u5b78\u53f0\u5317\u6821\u5340","school_id":"66","county_id":"1","place_id":"ChIJHc9n2hqsQjQR57Qq0sg0-h8","latitude":"25.0846197","longitude":"121.5457421"},
      {"id":"81","name":"\u671d\u967d\u79d1\u6280\u5927\u5b78","school_id":"67","county_id":"9","place_id":"ChIJJ874X6okaTQRBanKrGxJyAc","latitude":"24.069678","longitude":"120.714829"},
      {"id":"82","name":"\u9ad8\u96c4\u91ab\u5b78\u5927\u5b78","school_id":"68","county_id":"16","place_id":"ChIJLzY2b-UEbjQR3_tkbQye9oQ","latitude":"22.6473733","longitude":"120.3097772"},
      {"id":"83","name":"\u5357\u83ef\u5927\u5b78","school_id":"69","county_id":"13","place_id":"ChIJVd4HcQ-_bjQRxKEzp_i2vG0","latitude":"23.5693126","longitude":"120.4943064"},
      {"id":"84","name":"\u771f\u7406\u5927\u5b78","school_id":"70","county_id":"3","place_id":"ChIJhyC8xVGlQjQRqDxQ0tDN92M","latitude":"25.1769173","longitude":"121.4351497"},
      {"id":"85","name":"\u5927\u540c\u5927\u5b78","school_id":"71","county_id":"1","place_id":"ChIJK2wJmUWpQjQRRBQQ2b863DE","latitude":"25.0668881","longitude":"121.5222432"},
      {"id":"86","name":"\u5357\u81fa\u79d1\u6280\u5927\u5b78","school_id":"72","county_id":"15","place_id":"ChIJpcuVKR93bjQR7_9GHp9E_Ts","latitude":"23.0235764","longitude":"120.2247853"},
      {"id":"87","name":"\u5d11\u5c71\u79d1\u6280\u5927\u5b78","school_id":"73","county_id":"15","place_id":"ChIJUVU8ETNxbjQR1vXw_LnNGmw","latitude":"22.998268","longitude":"120.253104"},
      {"id":"88","name":"\u5609\u5357\u85e5\u7406\u5927\u5b78","school_id":"74","county_id":"15","place_id":"ChIJa7Pec-10bjQRMhD8fFCDFsI","latitude":"22.921847","longitude":"120.226466"},
      {"id":"89","name":"\u6a39\u5fb7\u79d1\u6280\u5927\u5b78","school_id":"75","county_id":"16","place_id":"ChIJ6_sfNI4RbjQR9mZvoZOypes","latitude":"22.7632038","longitude":"120.3757461"},
      {"id":"90","name":"\u6148\u6fdf\u5927\u5b78","school_id":"76","county_id":"20","place_id":"ChIJ02bxdq6faDQRwT6EgGbo-SY","latitude":"23.9927924","longitude":"121.5912738"},
      {"id":"91","name":"\u53f0\u5317\u91ab\u5b78\u5927\u5b78","school_id":"77","county_id":"1","place_id":"ChIJc0oGx0qqQjQRaPgxjLJI9qw","latitude":"25.025354","longitude":"121.561618"},
      {"id":"92","name":"\u4e2d\u5c71\u91ab\u5b78\u5927\u5b78","school_id":"78","county_id":"9","place_id":"ChIJNwE8JUw8aTQR0JV95gXT5UA","latitude":"24.1225235","longitude":"120.650412"},
      {"id":"93","name":"\u9f8d\u83ef\u79d1\u6280\u5927\u5b78","school_id":"79","county_id":"7","place_id":"ChIJLxezA38daDQRjNAdHRMwUjs","latitude":"25.0184744","longitude":"121.4026326"},
      {"id":"94","name":"\u8f14\u82f1\u79d1\u6280\u5927\u5b78","school_id":"80","county_id":"16","place_id":"ChIJCfkb_oEbbjQRqSsuG8NYQ4g","latitude":"22.6026893","longitude":"120.3896885"},
      {"id":"95","name":"\u660e\u65b0\u79d1\u6280\u5927\u5b78","school_id":"81","county_id":"6","place_id":"ChIJOyio-lQxaDQR73SlZFUcy5I","latitude":"24.8641986","longitude":"120.9906648"},
      {"id":"96","name":"\u9577\u69ae\u5927\u5b78","school_id":"82","county_id":"15","place_id":"ChIJzWTJFGtzbjQRI7ySQbstGps","latitude":"22.905029","longitude":"120.27265"},
      {"id":"97","name":"\u5f18\u5149\u79d1\u6280\u5927\u5b78","school_id":"83","county_id":"9","place_id":"ChIJCw8lNswUaTQRhjHJFrhlKbc","latitude":"24.2172822","longitude":"120.5807518"},
      {"id":"98","name":"\u4e2d\u570b\u91ab\u85e5\u5927\u5b78","school_id":"84","county_id":"9","place_id":"ChIJWy8MRWQ9aTQRAOPyHMJpOKY","latitude":"24.1562767","longitude":"120.6801328"},
      {"id":"99","name":"\u5065\u884c\u79d1\u6280\u5927\u5b78","school_id":"85","county_id":"7","place_id":"ChIJURfHh08iaDQRHe01BwAFMmw","latitude":"24.947282","longitude":"121.2290971"},
      {"id":"100","name":"\u6b63\u4fee\u79d1\u6280\u5927\u5b78","school_id":"86","county_id":"16","place_id":"ChIJOXuncNYabjQRwE3rK4A-5tU","latitude":"22.650984","longitude":"120.3489274"},
      {"id":"101","name":"\u842c\u80fd\u79d1\u6280\u5927\u5b78","school_id":"87","county_id":"7","place_id":"ChIJ7-XNHZEhaDQRZ-Y1kPIfzUA","latitude":"24.9909061","longitude":"121.2333651"},
      {"id":"102","name":"\u7384\u5958\u5927\u5b78","school_id":"88","county_id":"5","place_id":"ChIJ2S1UyolKaDQRJ4iIkTDUjIM","latitude":"24.7745463","longitude":"120.9423235"},
      {"id":"103","name":"\u5efa\u570b\u79d1\u6280\u5927\u5b78","school_id":"89","county_id":"10","place_id":"ChIJD1O1J4s4aTQR7797LDnH9GM","latitude":"24.066107","longitude":"120.549934"},
      {"id":"104","name":"\u660e\u5fd7\u79d1\u6280\u5927\u5b78","school_id":"90","county_id":"3","place_id":"ChIJqXFQS76nQjQRIJKWqB-zkbU","latitude":"25.0417279","longitude":"121.4206147"},
      {"id":"105","name":"\u9ad8\u82d1\u79d1\u6280\u5927\u5b78","school_id":"91","county_id":"16","place_id":"ChIJqxH8s4kMbjQR3PCxUY7sL00","latitude":"22.840939","longitude":"120.264623"},
      {"id":"106","name":"\u5927\u4ec1\u79d1\u6280\u5927\u5b78","school_id":"92","county_id":"18","place_id":"ChIJXSUX8eU9bjQRMWpdoPEW9P8","latitude":"22.726916","longitude":"120.542329"},
      {"id":"107","name":"\u8056\u7d04\u7ff0\u79d1\u6280\u5927\u5b78","school_id":"93","county_id":"3","place_id":"ChIJkT8DF4GwQjQRNUTDK-Z247o","latitude":"25.2275092","longitude":"121.4515876"},
      {"id":"108","name":"\u5dba\u6771\u79d1\u6280\u5927\u5b78","school_id":"94","county_id":"9","place_id":"ChIJRyl4S30-aTQRw-PkUK6TJKA","latitude":"24.137825","longitude":"120.609567"},
      {"id":"109","name":"\u4e2d\u570b\u79d1\u6280\u5927\u5b78","school_id":"95","county_id":"1","place_id":"ChIJxXu3uxOqQjQRTbaiuUN7E9U","latitude":"24.9993265","longitude":"121.5553455"},
      {"id":"110","name":"\u4e2d\u81fa\u79d1\u6280\u5927\u5b78","school_id":"96","county_id":"9","place_id":"ChIJz46-PUAYaTQRppa3rXcqspQ","latitude":"24.173051","longitude":"120.7355399"},
      {"id":"111","name":"\u4e9e\u6d32\u5927\u5b78","school_id":"97","county_id":"9","place_id":"ChIJa3OdqRc7aTQRyZ3IzXAdRxw","latitude":"24.0461431","longitude":"120.6874051"},
      {"id":"112","name":"\u958b\u5357\u5927\u5b78","school_id":"98","county_id":"7","place_id":"ChIJE8ohJoIfaDQRL4b-Jkz4994","latitude":"25.0112262","longitude":"121.2701938"},
      {"id":"113","name":"\u4f5b\u5149\u5927\u5b78","school_id":"99","county_id":"4","place_id":"ChIJC_DVbEPvZzQRGp6FOOrm-KQ","latitude":"24.8164113","longitude":"121.7236181"},
      {"id":"114","name":"\u53f0\u5357\u61c9\u7528\u79d1\u6280\u5927\u5b78","school_id":"100","county_id":"15","place_id":"ChIJxcR_wkd3bjQRQNiICLQ28wg","latitude":"23.0389432","longitude":"120.2393106"},
      {"id":"115","name":"\u9060\u6771\u79d1\u6280\u5927\u5b78","school_id":"101","county_id":"15","place_id":"ChIJiaQ2D2F6bjQRY7L61qdzDew","latitude":"23.0645351","longitude":"120.2944186"},
      {"id":"116","name":"\u5143\u57f9\u91ab\u4e8b\u79d1\u6280\u5927\u5b78","school_id":"102","county_id":"5","place_id":"ChIJk_Mp54dKaDQR_DRQKWAIAE0","latitude":"24.776337","longitude":"120.9428296"},
      {"id":"117","name":"\u666f\u6587\u79d1\u6280\u5927\u5b78","school_id":"103","county_id":"3","place_id":"ChIJB1D9lrQDaDQRV04ZJKIBe8A","latitude":"24.9513831","longitude":"121.5095218"},
      {"id":"118","name":"\u4e2d\u83ef\u91ab\u4e8b\u79d1\u6280\u5927\u5b78","school_id":"104","county_id":"15","place_id":"ChIJM7u2Vw90bjQRDGy4_AZ3bIU","latitude":"22.9608038","longitude":"120.2451253"},
      {"id":"119","name":"\u6771\u5357\u79d1\u6280\u5927\u5b78","school_id":"105","county_id":"3","place_id":"ChIJ9w0FPeiqQjQR3IVJO9lLVMM","latitude":"25.0039396","longitude":"121.6042031"},
      {"id":"120","name":"\u5fb7\u660e\u8ca1\u7d93\u79d1\u6280\u5927\u5b78","school_id":"106","county_id":"1","place_id":"ChIJwWiz0GusQjQRdm2lr_nkiPo","latitude":"25.0864973","longitude":"121.5655655"},
      {"id":"121","name":"\u660e\u9053\u5927\u5b78","school_id":"107","county_id":"10","place_id":"ChIJqzHFS85KaTQREA0NI7SjQNY","latitude":"23.8693105","longitude":"120.4950348"},
      {"id":"122","name":"\u5357\u958b\u79d1\u6280\u5927\u5b78","school_id":"108","county_id":"11","place_id":"ChIJUZZWqgQwaTQRWZF75jdrsXk","latitude":"23.9792331","longitude":"120.696843"},
      {"id":"123","name":"\u4e2d\u83ef\u79d1\u6280\u5927\u5b78","school_id":"109","county_id":"1","place_id":"ChIJh90goz6rQjQRG_ju86ZWDJ8","latitude":"25.0336571","longitude":"121.6099018"},
      {"id":"124","name":"\u50d1\u5149\u79d1\u6280\u5927\u5b78","school_id":"110","county_id":"9","place_id":"ChIJ5fJWPz4WaTQRQdbt-qRFJHA","latitude":"24.1890513","longitude":"120.6443696"},
      {"id":"125","name":"\u80b2\u9054\u79d1\u6280\u5927\u5b78","school_id":"111","county_id":"8","place_id":"ChIJvRtLlGSyaTQRXU1aIeVZTf8","latitude":"24.6509745","longitude":"120.8422629"},
      {"id":"126","name":"\u7f8e\u548c\u79d1\u6280\u5927\u5b78","school_id":"112","county_id":"18","place_id":"ChIJFxfKUFgibjQRHcruu2BFdCo","latitude":"22.603895","longitude":"120.560668"},
      {"id":"127","name":"\u5433\u9cf3\u79d1\u6280\u5927\u5b78","school_id":"113","county_id":"13","place_id":"ChIJT1V1mQC-bjQRLZGkqlnjKi0","latitude":"23.5360276","longitude":"120.4341554"},
      {"id":"128","name":"\u74b0\u7403\u79d1\u6280\u5927\u5b78","school_id":"114","county_id":"14","place_id":"ChIJmUh80XbIbjQRhnMYd_FgTHc","latitude":"23.679845","longitude":"120.5533425"},
      {"id":"129","name":"\u53f0\u7063\u9996\u5e9c\u5927\u5b78","school_id":"115","county_id":"15","place_id":"ChIJi0CTwMV9bjQR7dEVSKCdxKk","latitude":"23.1930713","longitude":"120.2684501"},
      {"id":"130","name":"\u4e2d\u5dde\u79d1\u6280\u5927\u5b78","school_id":"116","county_id":"10","place_id":"ChIJX4JfU9o2aTQR1ezg_AGpNAg","latitude":"23.9579","longitude":"120.604196"},
      {"id":"131","name":"\u4fee\u5e73\u79d1\u6280\u5927\u5b78","school_id":"117","county_id":"9","place_id":"ChIJeeSZ4DQjaTQRsZsEG7WHADo","latitude":"24.095253","longitude":"120.7138155"},
      {"id":"132","name":"\u9577\u5e9a\u79d1\u6280\u5927\u5b78","school_id":"118","county_id":"7","place_id":"ChIJIR_3XnunQjQRSAjRIIToS5I","latitude":"25.0307388","longitude":"121.3896892"},
      {"id":"133","name":"\u53f0\u5317\u57ce\u5e02\u79d1\u6280\u5927\u5b78","school_id":"119","county_id":"1","place_id":"ChIJ9WAXS3WvQjQRuck3rbarxWM","latitude":"25.133617","longitude":"121.468879"},
      {"id":"134","name":"\u5927\u83ef\u79d1\u6280\u5927\u5b78","school_id":"120","county_id":"6","place_id":"ChIJDzHr0CI4aDQRJg0vPvf7eT0","latitude":"24.777438","longitude":"121.090208"},
      {"id":"135","name":"\u9192\u543e\u79d1\u6280\u5927\u5b78","school_id":"121","county_id":"3","place_id":"ChIJAaoNZfamQjQRzNNp-pu0hiU","latitude":"25.0810853","longitude":"121.3965327"},
      {"id":"136","name":"\u5357\u69ae\u79d1\u6280\u5927\u5b78","school_id":"122","county_id":"15","place_id":"ChIJTT2M9j2EbjQRO_9RyYY6NyY","latitude":"23.323718","longitude":"120.274889"},
      {"id":"137","name":"\u6587\u85fb\u5916\u8a9e\u5927\u5b78","school_id":"123","county_id":"16","place_id":"ChIJoYRBThYFbjQRsS72Ukzs78M","latitude":"22.6703488","longitude":"120.3191403"},
      {"id":"138","name":"\u83ef\u590f\u79d1\u6280\u5927\u5b78","school_id":"124","county_id":"3","place_id":"ChIJdz0wTGkCaDQRcbT11MDya4A","latitude":"24.981084","longitude":"121.50752"},
      {"id":"139","name":"\u6148\u6fdf\u79d1\u6280\u5927\u5b78","school_id":"125","county_id":"20","place_id":"ChIJ357IixmfaDQRASA2I2WliOM","latitude":"23.996638","longitude":"121.5651"},
      {"id":"140","name":"\u81f4\u7406\u79d1\u6280\u5927\u5b78","school_id":"126","county_id":"3","place_id":"ChIJdbgz-haoQjQRsOYM2G9Qb9I","latitude":"25.0210986","longitude":"121.4651279"},
      {"id":"141","name":"\u5eb7\u5be7\u5927\u5b78","school_id":"127","county_id":"15","place_id":"ChIJgWcK6wvYbTQRAs4SOo_UiNM","latitude":"23.0603505","longitude":"120.1559952"},
      {"id":"142","name":"\u4e2d\u4fe1\u91d1\u878d\u7ba1\u7406\u5b78\u9662","school_id":"128","county_id":"15","place_id":"ChIJS1tnMP13bjQRw7cb_bBJk58","latitude":"23.0639816","longitude":"120.1626834"},
      {"id":"143","name":"\u5927\u6f22\u6280\u8853\u5b78\u9662","school_id":"129","county_id":"20","place_id":"ChIJU5o5IxOeaDQRjvc0QgZmwHk","latitude":"24.0392796","longitude":"121.6052322"},
      {"id":"144","name":"\u548c\u6625\u6280\u8853\u5b78\u9662","school_id":"130","county_id":"16","place_id":"ChIJNSBpX-YbbjQR9ZiqCjoMQqE","latitude":"22.6080409","longitude":"120.4270968"},
      {"id":"145","name":"\u4e9e\u6771\u6280\u8853\u5b78\u9662","school_id":"131","county_id":"3","place_id":"ChIJ-_IKP7ECaDQRaWUjFKdH22Q","latitude":"24.9951546","longitude":"121.4531795"},
      {"id":"146","name":"\u5357\u4e9e\u6280\u8853\u5b78\u9662","school_id":"132","county_id":"7","place_id":"ChIJFXnftGQiaDQRTcePXcB54bk","latitude":"24.937167","longitude":"121.251748"},
      {"id":"147","name":"\u7a3b\u6c5f\u79d1\u6280\u66a8\u7ba1\u7406\u5b78\u9662","school_id":"133","county_id":"13","place_id":"ChIJbVkPB7GbbjQRI6UXq-LslCg","latitude":"23.4487766","longitude":"120.2896634"},
      {"id":"148","name":"\u5b8f\u570b\u5fb7\u9716\u79d1\u6280\u5927\u5b78","school_id":"134","county_id":"3","place_id":"ChIJgzcktdACaDQR8yCQsJiJUZ8","latitude":"24.972325","longitude":"121.4557677"},
      {"id":"149","name":"\u862d\u967d\u6280\u8853\u5b78\u9662","school_id":"135","county_id":"4","place_id":"ChIJX_-Nwmb3ZzQRSyPeACZ6ir4","latitude":"24.864987","longitude":"121.817719"},
      {"id":"150","name":"\u9ece\u660e\u6280\u8853\u5b78\u9662","school_id":"136","county_id":"3","place_id":"ChIJFW7a7EmmQjQRg0qkN7wrPZc","latitude":"25.0657896","longitude":"121.4200576"},
      {"id":"151","name":"\u6771\u65b9\u8a2d\u8a08\u5927\u5b78","school_id":"137","county_id":"16","place_id":"ChIJxzvU9FMLbjQR9sYi2aEjBXI","latitude":"22.8807003","longitude":"120.2454082"},
      {"id":"152","name":"\u7d93\u570b\u7ba1\u7406\u66a8\u5065\u5eb7\u5b78\u9662","school_id":"138","county_id":"2","place_id":"ChIJUQzyr3tOXTQRDECBovasq-w","latitude":"25.1497642","longitude":"121.7284558"},
      {"id":"153","name":"\u5d07\u53f3\u5f71\u85dd\u79d1\u6280\u5927\u5b78","school_id":"139","county_id":"2","place_id":"ChIJLaS0cEhOXTQRJeeSXkyRCa4","latitude":"25.13236","longitude":"121.75426"},
      {"id":"154","name":"\u5927\u540c\u6280\u8853\u5b78\u9662\u5609\u7fa9\u6821\u5340","school_id":"140","county_id":"12","place_id":"ChIJseq_YkaUbjQRUEL97jcySRc","latitude":"23.4697844","longitude":"120.464758"},
      {"id":"155","name":"\u5927\u540c\u6280\u8853\u5b78\u9662\u592a\u4fdd\u6821\u5340","school_id":"140","county_id":"13","place_id":"ChIJtQhYK7SbbjQRt67yNz2V2Qg","latitude":"23.451648","longitude":"120.291699"},
      {"id":"156","name":"\u4e9e\u592a\u5275\u610f\u6280\u8853\u5b78\u9662","school_id":"141","county_id":"8","place_id":"ChIJsd10gBFMaDQRcOy5tU0wqPk","latitude":"24.68257","longitude":"120.968985"},
      {"id":"157","name":"\u53f0\u7063\u89c0\u5149\u5b78\u9662","school_id":"142","county_id":"20","place_id":"ChIJCYp8if6kaDQR67FTUmkkvEs","latitude":"23.8582378","longitude":"121.4860703"},
      {"id":"158","name":"\u99ac\u5055\u91ab\u5b78\u9662","school_id":"143","county_id":"3","place_id":"ChIJ11kXPSuxQjQRhnSCSnoGQvw","latitude":"25.254377","longitude":"121.4950804"},
      {"id":"159","name":"\u6cd5\u9f13\u6587\u7406\u5b78\u9662","school_id":"144","county_id":"3","place_id":"ChIJP37Pibe0QjQRGdExJZ9Sv7I","latitude":"25.245412","longitude":"121.6169569"},
      {"id":"160","name":"\u53f0\u5317\u6d77\u6d0b\u79d1\u6280\u5927\u5b78","school_id":"145","county_id":"3","place_id":"ChIJIUbnj7a6QjQR-70GE2k29R4","latitude":"25.191411","longitude":"121.427199"},
      {"id":"161","name":"\u57fa\u7763\u6559\u53f0\u7063\u6d78\u4fe1\u6703\u795e\u5b78\u9662","school_id":"146","county_id":"1","place_id":"ChIJ0RODkkyqQjQR5pu-Ki2-8zU","latitude":"25.023742","longitude":"121.566763"},
      {"id":"162","name":"\u53f0\u5317\u57fa\u7763\u5b78\u9662","school_id":"147","county_id":"3","place_id":"ChIJZ-Tax3avQjQRmUpEZ46jtD8","latitude":"25.130922","longitude":"121.461205"},
      {"id":"163","name":"\u4e00\u8cab\u9053\u5929\u7687\u5b78\u9662","school_id":"148","county_id":"16","place_id":"ChIJRQhA8FRBbjQRNbkOGbIASK4","latitude":"22.8892261","longitude":"120.6177418"},
      {"id":"164","name":"\u53f0\u7063\u795e\u5b78\u9662","school_id":"149","county_id":"1","place_id":"ChIJo1urySasQjQRT_AOEvWEcQ8","latitude":"25.101234","longitude":"121.541213"},
      {"id":"165","name":"\u5d07\u5fb7\u5b78\u9662","school_id":"150","county_id":"11","place_id":"ChIJm0-iVTLaaDQRyaHloZZDCNQ","latitude":"23.9609184","longitude":"121.0017614"},
      {"id":"166","name":"\u53f0\u5317\u5e02\u7acb\u5927\u5b78","school_id":"151","county_id":"1","place_id":"ChIJRd1TL6CpQjQRRTht3W5d8Dg","latitude":"25.0355353","longitude":"121.5135416"},
      {"id":"167","name":"\u9ad8\u96c4\u5e02\u7acb\u7a7a\u4e2d\u5927\u5b78","school_id":"152","county_id":"16","place_id":"ChIJwcQkA9UcbjQRLRum6EvJCcI","latitude":"22.5668767","longitude":"120.3458825"},
      {"id":"168","name":"\u9678\u8ecd\u8ecd\u5b98\u5b78\u6821","school_id":"153","county_id":"16","place_id":"ChIJgRE962sbbjQRycu6KziMKsM","latitude":"22.6193076","longitude":"120.3654449"},
      {"id":"169","name":"\u4e2d\u83ef\u6c11\u570b\u6d77\u8ecd\u8ecd\u5b98\u5b78\u6821","school_id":"154","county_id":"16","place_id":"ChIJbwBuJHwPbjQRj9ttecsei-M","latitude":"22.7057392","longitude":"120.2905709"},
      {"id":"170","name":"\u4e2d\u83ef\u6c11\u570b\u7a7a\u8ecd\u8ecd\u5b98\u5b78\u6821","school_id":"155","county_id":"16","place_id":"ChIJ30EyObsObjQRp3lLsBhaohw","latitude":"22.7834793","longitude":"120.2707306"},
      {"id":"171","name":"\u570b\u9632\u5927\u5b78\u7387\u771f\u6821\u5340","school_id":"156","county_id":"7","place_id":"ChIJoQjgS-EYaDQRi4_G6t3MbeM","latitude":"24.9347793","longitude":"121.3030591"},
      {"id":"172","name":"\u570b\u9632\u5927\u5b78\u4e2d\u6b63\u5dba\u6821\u5340","school_id":"156","county_id":"7","place_id":"ChIJnc2H4fsXaDQRWiJJnB5_8Gw","latitude":"24.878564","longitude":"121.266463"},
      {"id":"173","name":"\u4e2d\u592e\u8b66\u5bdf\u5927\u5b78","school_id":"157","county_id":"7","place_id":"ChIJxU75_LKgQjQRt-d2xXt_a1o","latitude":"25.047233","longitude":"121.352376"},
      {"id":"174","name":"\u570b\u9632\u91ab\u5b78\u9662","school_id":"158","county_id":"1","place_id":"ChIJCfH-UH-sQjQRt69Usepu9Iw","latitude":"25.0711904","longitude":"121.595408"},
      {"id":"175","name":"\u7a7a\u8ecd\u822a\u7a7a\u6280\u8853\u5b78\u9662","school_id":"159","county_id":"16","place_id":"ChIJAeStAJkObjQRgX3OofJaOKc","latitude":"22.7860693","longitude":"120.2784898"}
    ]
  }
  ,{"type":"table","name":"county","database":"mobilehome","data":
    [
      {"id":"1","name":"\u53f0\u5317\u5e02","region_id":"1"},
      {"id":"2","name":"\u57fa\u9686\u5e02","region_id":"1"},
      {"id":"3","name":"\u65b0\u5317\u5e02","region_id":"1"},
      {"id":"4","name":"\u5b9c\u862d\u7e23","region_id":"1"},
      {"id":"5","name":"\u65b0\u7af9\u5e02","region_id":"1"},
      {"id":"6","name":"\u65b0\u7af9\u7e23","region_id":"1"},
      {"id":"7","name":"\u6843\u5712\u5e02","region_id":"1"},
      {"id":"8","name":"\u82d7\u6817\u7e23","region_id":"2"},
      {"id":"9","name":"\u53f0\u4e2d\u5e02","region_id":"2"},
      {"id":"10","name":"\u5f70\u5316\u7e23","region_id":"2"},
      {"id":"11","name":"\u5357\u6295\u7e23","region_id":"2"},
      {"id":"12","name":"\u5609\u7fa9\u5e02","region_id":"3"},
      {"id":"13","name":"\u5609\u7fa9\u7e23","region_id":"3"},
      {"id":"14","name":"\u96f2\u6797\u7e23","region_id":"2"},
      {"id":"15","name":"\u53f0\u5357\u5e02","region_id":"3"},
      {"id":"16","name":"\u9ad8\u96c4\u5e02","region_id":"3"},
      {"id":"17","name":"\u6f8e\u6e56\u7e23","region_id":"3"},
      {"id":"18","name":"\u5c4f\u6771\u7e23","region_id":"3"},
      {"id":"19","name":"\u53f0\u6771\u7e23","region_id":"4"},
      {"id":"20","name":"\u82b1\u84ee\u7e23","region_id":"4"},
      {"id":"21","name":"\u91d1\u9580\u7e23","region_id":"4"},
      {"id":"22","name":"\u9023\u6c5f\u7e23","region_id":"4"}
    ]
  }
  ,{"type":"table","name":"region","database":"mobilehome","data":
    [
      {"id":"1","name":"\u5317\u90e8"},
      {"id":"2","name":"\u4e2d\u90e8"},
      {"id":"3","name":"\u5357\u90e8"},
      {"id":"4","name":"\u6771\u90e8"}
    ]
  }
  ,{"type":"table","name":"school","database":"mobilehome","data":
    [
      {"id":"1","name":"\u570b\u7acb\u653f\u6cbb\u5927\u5b78"},
      {"id":"2","name":"\u570b\u7acb\u6e05\u83ef\u5927\u5b78"},
      {"id":"3","name":"\u570b\u7acb\u53f0\u7063\u5927\u5b78"},
      {"id":"4","name":"\u570b\u7acb\u53f0\u7063\u5e2b\u7bc4\u5927\u5b78"},
      {"id":"5","name":"\u570b\u7acb\u6210\u529f\u5927\u5b78"},
      {"id":"6","name":"\u570b\u7acb\u4e2d\u8208\u5927\u5b78"},
      {"id":"7","name":"\u570b\u7acb\u4ea4\u901a\u5927\u5b78"},
      {"id":"8","name":"\u570b\u7acb\u4e2d\u592e\u5927\u5b78"},
      {"id":"9","name":"\u570b\u7acb\u4e2d\u5c71\u5927\u5b78"},
      {"id":"10","name":"\u570b\u7acb\u53f0\u7063\u6d77\u6d0b\u5927\u5b78"},
      {"id":"11","name":"\u570b\u7acb\u4e2d\u6b63\u5927\u5b78"},
      {"id":"12","name":"\u570b\u7acb\u9ad8\u96c4\u5e2b\u7bc4\u5927\u5b78"},
      {"id":"13","name":"\u570b\u7acb\u5f70\u5316\u5e2b\u7bc4\u5927\u5b78"},
      {"id":"14","name":"\u570b\u7acb\u967d\u660e\u5927\u5b78"},
      {"id":"15","name":"\u570b\u7acb\u53f0\u5317\u5927\u5b78"},
      {"id":"16","name":"\u570b\u7acb\u5609\u7fa9\u5927\u5b78"},
      {"id":"17","name":"\u570b\u7acb\u9ad8\u96c4\u5927\u5b78"},
      {"id":"18","name":"\u570b\u7acb\u6771\u83ef\u5927\u5b78"},
      {"id":"19","name":"\u570b\u7acb\u66a8\u5357\u570b\u969b\u5927\u5b78"},
      {"id":"20","name":"\u570b\u7acb\u53f0\u7063\u79d1\u6280\u5927\u5b78"},
      {"id":"21","name":"\u570b\u7acb\u96f2\u6797\u79d1\u6280\u5927\u5b78"},
      {"id":"22","name":"\u570b\u7acb\u5c4f\u6771\u79d1\u6280\u5927\u5b78"},
      {"id":"23","name":"\u570b\u7acb\u53f0\u5317\u79d1\u6280\u5927\u5b78"},
      {"id":"24","name":"\u570b\u7acb\u9ad8\u96c4\u7b2c\u4e00\u79d1\u6280\u5927\u5b78"},
      {"id":"25","name":"\u570b\u7acb\u9ad8\u96c4\u61c9\u7528\u79d1\u6280\u5927\u5b78"},
      {"id":"26","name":"\u570b\u7acb\u53f0\u5317\u85dd\u8853\u5927\u5b78"},
      {"id":"27","name":"\u570b\u7acb\u53f0\u7063\u85dd\u8853\u5927\u5b78"},
      {"id":"28","name":"\u570b\u7acb\u53f0\u6771\u5927\u5b78"},
      {"id":"29","name":"\u570b\u7acb\u5b9c\u862d\u5927\u5b78"},
      {"id":"30","name":"\u570b\u7acb\u806f\u5408\u5927\u5b78"},
      {"id":"31","name":"\u570b\u7acb\u864e\u5c3e\u79d1\u6280\u5927\u5b78"},
      {"id":"32","name":"\u570b\u7acb\u9ad8\u96c4\u6d77\u6d0b\u79d1\u6280\u5927\u5b78"},
      {"id":"33","name":"\u570b\u7acb\u53f0\u5357\u85dd\u8853\u5927\u5b78"},
      {"id":"34","name":"\u570b\u7acb\u53f0\u5357\u5927\u5b78"},
      {"id":"35","name":"\u570b\u7acb\u53f0\u5317\u6559\u80b2\u5927\u5b78"},
      {"id":"36","name":"\u570b\u7acb\u65b0\u7af9\u6559\u80b2\u5927\u5b78"},
      {"id":"37","name":"\u570b\u7acb\u53f0\u4e2d\u6559\u80b2\u5927\u5b78"},
      {"id":"38","name":"\u570b\u7acb\u6f8e\u6e56\u79d1\u6280\u5927\u5b78"},
      {"id":"39","name":"\u570b\u7acb\u52e4\u76ca\u79d1\u6280\u5927\u5b78"},
      {"id":"40","name":"\u570b\u7acb\u9ad4\u80b2\u5927\u5b78"},
      {"id":"41","name":"\u570b\u7acb\u53f0\u5317\u8b77\u7406\u5065\u5eb7\u5927\u5b78"},
      {"id":"42","name":"\u570b\u7acb\u9ad8\u96c4\u9910\u65c5\u5927\u5b78"},
      {"id":"43","name":"\u570b\u7acb\u91d1\u9580\u5927\u5b78"},
      {"id":"44","name":"\u570b\u7acb\u53f0\u7063\u9ad4\u80b2\u904b\u52d5\u5927\u5b78"},
      {"id":"45","name":"\u570b\u7acb\u53f0\u4e2d\u79d1\u6280\u5927\u5b78"},
      {"id":"46","name":"\u570b\u7acb\u53f0\u5317\u5546\u696d\u5927\u5b78"},
      {"id":"47","name":"\u570b\u7acb\u5c4f\u6771\u5927\u5b78"},
      {"id":"48","name":"\u570b\u7acb\u53f0\u7063\u6232\u66f2\u5b78\u9662"},
      {"id":"49","name":"\u570b\u7acb\u7a7a\u4e2d\u5927\u5b78"},
      {"id":"50","name":"\u6771\u6d77\u5927\u5b78"},
      {"id":"51","name":"\u8f14\u4ec1\u5927\u5b78"},
      {"id":"52","name":"\u6771\u5433\u5927\u5b78"},
      {"id":"53","name":"\u4e2d\u539f\u5927\u5b78"},
      {"id":"54","name":"\u6de1\u6c5f\u5927\u5b78"},
      {"id":"55","name":"\u4e2d\u570b\u6587\u5316\u5927\u5b78"},
      {"id":"56","name":"\u9022\u7532\u5927\u5b78"},
      {"id":"57","name":"\u975c\u5b9c\u5927\u5b78"},
      {"id":"58","name":"\u9577\u5e9a\u5927\u5b78"},
      {"id":"59","name":"\u5143\u667a\u5927\u5b78"},
      {"id":"60","name":"\u4e2d\u83ef\u5927\u5b78"},
      {"id":"61","name":"\u5927\u8449\u5927\u5b78"},
      {"id":"62","name":"\u83ef\u68b5\u5927\u5b78"},
      {"id":"63","name":"\u7fa9\u5b88\u5927\u5b78"},
      {"id":"64","name":"\u4e16\u65b0\u5927\u5b78"},
      {"id":"65","name":"\u9298\u50b3\u5927\u5b78"},
      {"id":"66","name":"\u5be6\u8e10\u5927\u5b78"},
      {"id":"67","name":"\u671d\u967d\u79d1\u6280\u5927\u5b78"},
      {"id":"68","name":"\u9ad8\u96c4\u91ab\u5b78\u5927\u5b78"},
      {"id":"69","name":"\u5357\u83ef\u5927\u5b78"},
      {"id":"70","name":"\u771f\u7406\u5927\u5b78"},
      {"id":"71","name":"\u5927\u540c\u5927\u5b78"},
      {"id":"72","name":"\u5357\u81fa\u79d1\u6280\u5927\u5b78"},
      {"id":"73","name":"\u5d11\u5c71\u79d1\u6280\u5927\u5b78"},
      {"id":"74","name":"\u5609\u85e5\u5b78\u6821\u8ca1\u5718\u6cd5\u4eba\u5609\u5357\u85e5\u7406\u5927\u5b78"},
      {"id":"75","name":"\u6a39\u5fb7\u79d1\u6280\u5927\u5b78"},
      {"id":"76","name":"\u6148\u6fdf\u5b78\u6821\u8ca1\u5718\u6cd5\u4eba\u6148\u6fdf\u5927\u5b78"},
      {"id":"77","name":"\u53f0\u5317\u91ab\u5b78\u5927\u5b78"},
      {"id":"78","name":"\u4e2d\u5c71\u91ab\u5b78\u5927\u5b78"},
      {"id":"79","name":"\u9f8d\u83ef\u79d1\u6280\u5927\u5b78"},
      {"id":"80","name":"\u8f14\u82f1\u79d1\u6280\u5927\u5b78"},
      {"id":"81","name":"\u660e\u65b0\u79d1\u6280\u5927\u5b78"},
      {"id":"82","name":"\u9577\u69ae\u5927\u5b78"},
      {"id":"83","name":"\u5f18\u5149\u79d1\u6280\u5927\u5b78"},
      {"id":"84","name":"\u4e2d\u570b\u91ab\u85e5\u5927\u5b78"},
      {"id":"85","name":"\u5065\u884c\u5b78\u6821\u8ca1\u5718\u6cd5\u4eba\u5065\u884c\u79d1\u6280\u5927\u5b78"},
      {"id":"86","name":"\u6b63\u4fee\u5b78\u6821\u8ca1\u5718\u6cd5\u4eba\u6b63\u4fee\u79d1\u6280\u5927\u5b78"},
      {"id":"87","name":"\u842c\u80fd\u5b78\u6821\u8ca1\u5718\u6cd5\u4eba\u842c\u80fd\u79d1\u6280\u5927\u5b78"},
      {"id":"88","name":"\u7384\u5958\u5927\u5b78"},
      {"id":"89","name":"\u5efa\u570b\u79d1\u6280\u5927\u5b78"},
      {"id":"90","name":"\u660e\u5fd7\u79d1\u6280\u5927\u5b78"},
      {"id":"91","name":"\u9ad8\u82d1\u79d1\u6280\u5927\u5b78"},
      {"id":"92","name":"\u5927\u4ec1\u79d1\u6280\u5927\u5b78"},
      {"id":"93","name":"\u8056\u7d04\u7ff0\u79d1\u6280\u5927\u5b78"},
      {"id":"94","name":"\u5dba\u6771\u79d1\u6280\u5927\u5b78"},
      {"id":"95","name":"\u4e2d\u570b\u79d1\u6280\u5927\u5b78"},
      {"id":"96","name":"\u4e2d\u81fa\u79d1\u6280\u5927\u5b78"},
      {"id":"97","name":"\u4e9e\u6d32\u5927\u5b78"},
      {"id":"98","name":"\u958b\u5357\u5927\u5b78"},
      {"id":"99","name":"\u4f5b\u5149\u5927\u5b78"},
      {"id":"100","name":"\u53f0\u5357\u5bb6\u5c08\u5b78\u6821\u8ca1\u5718\u6cd5\u4eba\u53f0\u5357\u61c9\u7528\u79d1\u6280\u5927\u5b78"},
      {"id":"101","name":"\u9060\u6771\u79d1\u6280\u5927\u5b78"},
      {"id":"102","name":"\u5149\u5b87\u5b78\u6821\u8ca1\u5718\u6cd5\u4eba\u5143\u57f9\u91ab\u4e8b\u79d1\u6280\u5927\u5b78"},
      {"id":"103","name":"\u666f\u6587\u79d1\u6280\u5927\u5b78"},
      {"id":"104","name":"\u4e2d\u83ef\u91ab\u4e8b\u79d1\u6280\u5927\u5b78"},
      {"id":"105","name":"\u6771\u5357\u79d1\u6280\u5927\u5b78"},
      {"id":"106","name":"\u5fb7\u660e\u8ca1\u7d93\u79d1\u6280\u5927\u5b78"},
      {"id":"107","name":"\u660e\u9053\u5b78\u6821\u8ca1\u5718\u6cd5\u4eba\u660e\u9053\u5927\u5b78"},
      {"id":"108","name":"\u5357\u958b\u79d1\u6280\u5927\u5b78"},
      {"id":"109","name":"\u4e2d\u83ef\u5b78\u6821\u8ca1\u5718\u6cd5\u4eba\u4e2d\u83ef\u79d1\u6280\u5927\u5b78"},
      {"id":"110","name":"\u50d1\u5149\u79d1\u6280\u5927\u5b78"},
      {"id":"111","name":"\u5ee3\u4e9e\u5b78\u6821\u8ca1\u5718\u6cd5\u4eba\u80b2\u9054\u79d1\u6280\u5927\u5b78"},
      {"id":"112","name":"\u7f8e\u548c\u5b78\u6821\u8ca1\u5718\u6cd5\u4eba\u7f8e\u548c\u79d1\u6280\u5927\u5b78"},
      {"id":"113","name":"\u5433\u9cf3\u79d1\u6280\u5927\u5b78"},
      {"id":"114","name":"\u74b0\u7403\u5b78\u6821\u8ca1\u5718\u6cd5\u4eba\u74b0\u7403\u79d1\u6280\u5927\u5b78"},
      {"id":"115","name":"\u53f0\u7063\u9996\u5e9c\u5927\u5b78"},
      {"id":"116","name":"\u4e2d\u5dde\u5b78\u6821\u8ca1\u5718\u6cd5\u4eba\u4e2d\u5dde\u79d1\u6280\u5927\u5b78"},
      {"id":"117","name":"\u4fee\u5e73\u5b78\u6821\u8ca1\u5718\u6cd5\u4eba\u4fee\u5e73\u79d1\u6280\u5927\u5b78"},
      {"id":"118","name":"\u9577\u5e9a\u5b78\u6821\u8ca1\u5718\u6cd5\u4eba\u9577\u5e9a\u79d1\u6280\u5927\u5b78"},
      {"id":"119","name":"\u57ce\u5e02\u5b78\u6821\u8ca1\u5718\u6cd5\u4eba\u53f0\u5317\u57ce\u5e02\u79d1\u6280\u5927\u5b78"},
      {"id":"120","name":"\u5927\u83ef\u5b78\u6821\u8ca1\u5718\u6cd5\u4eba\u5927\u83ef\u79d1\u6280\u5927\u5b78"},
      {"id":"121","name":"\u9192\u543e\u5b78\u6821\u8ca1\u5718\u6cd5\u4eba\u9192\u543e\u79d1\u6280\u5927\u5b78"},
      {"id":"122","name":"\u5357\u69ae\u5b78\u6821\u8ca1\u5718\u6cd5\u4eba\u5357\u69ae\u79d1\u6280\u5927\u5b78"},
      {"id":"123","name":"\u6587\u85fb\u5b78\u6821\u8ca1\u5718\u6cd5\u4eba\u6587\u85fb\u5916\u8a9e\u5927\u5b78"},
      {"id":"124","name":"\u83ef\u590f\u5b78\u6821\u8ca1\u5718\u6cd5\u4eba\u83ef\u590f\u79d1\u6280\u5927\u5b78"},
      {"id":"125","name":"\u6148\u6fdf\u5b78\u6821\u8ca1\u5718\u6cd5\u4eba\u6148\u6fdf\u79d1\u6280\u5927\u5b78"},
      {"id":"126","name":"\u81f4\u7406\u5b78\u6821\u8ca1\u5718\u6cd5\u4eba\u81f4\u7406\u79d1\u6280\u5927\u5b78"},
      {"id":"127","name":"\u5eb7\u5be7\u5b78\u6821\u8ca1\u5718\u6cd5\u4eba\u5eb7\u5be7\u5927\u5b78"},
      {"id":"128","name":"\u4e2d\u4fe1\u5b78\u6821\u8ca1\u5718\u6cd5\u4eba\u4e2d\u4fe1\u91d1\u878d\u7ba1\u7406\u5b78\u9662"},
      {"id":"129","name":"\u5927\u6f22\u6280\u8853\u5b78\u9662"},
      {"id":"130","name":"\u548c\u6625\u6280\u8853\u5b78\u9662"},
      {"id":"131","name":"\u4e9e\u6771\u6280\u8853\u5b78\u9662"},
      {"id":"132","name":"\u5357\u4e9e\u79d1\u6280\u5b78\u6821\u8ca1\u5718\u6cd5\u4eba\u5357\u4e9e\u6280\u8853\u5b78\u9662"},
      {"id":"133","name":"\u7a3b\u6c5f\u79d1\u6280\u66a8\u7ba1\u7406\u5b78\u9662"},
      {"id":"134","name":"\u5b8f\u570b\u5fb7\u9716\u79d1\u6280\u5927\u5b78"},
      {"id":"135","name":"\u862d\u967d\u6280\u8853\u5b78\u9662"},
      {"id":"136","name":"\u9ece\u660e\u6280\u8853\u5b78\u9662"},
      {"id":"137","name":"\u6771\u65b9\u8a2d\u8a08\u5927\u5b78"},
      {"id":"138","name":"\u7d93\u570b\u7ba1\u7406\u66a8\u5065\u5eb7\u5b78\u9662"},
      {"id":"139","name":"\u5d07\u53f3\u5f71\u85dd\u79d1\u6280\u5927\u5b78"},
      {"id":"140","name":"\u5927\u540c\u6280\u8853\u5b78\u9662"},
      {"id":"141","name":"\u4e9e\u592a\u5b78\u6821\u8ca1\u5718\u6cd5\u4eba\u4e9e\u592a\u5275\u610f\u6280\u8853\u5b78\u9662"},
      {"id":"142","name":"\u53f0\u7063\u89c0\u5149\u5b78\u9662"},
      {"id":"143","name":"\u99ac\u5055\u5b78\u6821\u8ca1\u5718\u6cd5\u4eba\u99ac\u5055\u91ab\u5b78\u9662"},
      {"id":"144","name":"\u6cd5\u9f13\u5b78\u6821\u8ca1\u5718\u6cd5\u4eba\u6cd5\u9f13\u6587\u7406\u5b78\u9662"},
      {"id":"145","name":"\u53f0\u5317\u6d77\u6d0b\u79d1\u6280\u5927\u5b78"},
      {"id":"146","name":"\u5b78\u6821\u8ca1\u5718\u6cd5\u4eba\u4e2d\u83ef\u6d78\u4fe1\u6703\u57fa\u7763\u6559\u53f0\u7063\u6d78\u6703\u795e\u5b78"},
      {"id":"147","name":"\u53f0\u5317\u57fa\u7763\u5b78\u9662"},
      {"id":"148","name":"\u8ca1\u5718\u6cd5\u4eba\u4e00\u8cab\u9053\u5929\u7687\u57fa\u91d1\u6703\u4e00\u8cab\u9053\u5929\u7687\u5b78\u9662"},
      {"id":"149","name":"\u53f0\u7063\u795e\u5b78\u7814\u7a76\u5b78\u9662"},
      {"id":"150","name":"\u4e00\u8cab\u9053\u5d07\u5fb7\u5b78\u9662"},
      {"id":"151","name":"\u53f0\u5317\u5e02\u7acb\u5927\u5b78"},
      {"id":"152","name":"\u9ad8\u96c4\u5e02\u7acb\u7a7a\u4e2d\u5927\u5b78"},
      {"id":"153","name":"\u4e2d\u83ef\u6c11\u570b\u9678\u8ecd\u8ecd\u5b98\u5b78\u6821"},
      {"id":"154","name":"\u6d77\u8ecd\u8ecd\u5b98\u5b78\u6821"},
      {"id":"155","name":"\u4e2d\u83ef\u6c11\u570b\u7a7a\u8ecd\u8ecd\u5b98\u5b78\u6821"},
      {"id":"156","name":"\u570b\u9632\u5927\u5b78"},
      {"id":"157","name":"\u4e2d\u592e\u8b66\u5bdf\u5927\u5b78"},
      {"id":"158","name":"\u570b\u9632\u91ab\u5b78\u9662"},
      {"id":"159","name":"\u570b\u7acb\u7a7a\u8ecd\u822a\u7a7a\u6280\u8853\u5b78\u9662"}
    ]
  }
  ,{"type":"table","name":"town","database":"mobilehome","data":
    [
      {"id":"1","county_id":"1","name":"\u4e2d\u6b63\u5340","zip_code":"100"},
      {"id":"2","county_id":"1","name":"\u5927\u540c\u5340","zip_code":"103"},
      {"id":"3","county_id":"1","name":"\u4e2d\u5c71\u5340","zip_code":"104"},
      {"id":"4","county_id":"1","name":"\u677e\u5c71\u5340","zip_code":"105"},
      {"id":"5","county_id":"1","name":"\u5927\u5b89\u5340","zip_code":"106"},
      {"id":"6","county_id":"1","name":"\u842c\u83ef\u5340","zip_code":"108"},
      {"id":"7","county_id":"1","name":"\u4fe1\u7fa9\u5340","zip_code":"110"},
      {"id":"8","county_id":"1","name":"\u58eb\u6797\u5340","zip_code":"111"},
      {"id":"9","county_id":"1","name":"\u5317\u6295\u5340","zip_code":"112"},
      {"id":"10","county_id":"1","name":"\u5167\u6e56\u5340","zip_code":"114"},
      {"id":"11","county_id":"1","name":"\u5357\u6e2f\u5340","zip_code":"115"},
      {"id":"12","county_id":"1","name":"\u6587\u5c71\u5340","zip_code":"116"},
      {"id":"13","county_id":"2","name":"\u4ec1\u611b\u5340","zip_code":"200"},
      {"id":"14","county_id":"2","name":"\u4fe1\u7fa9\u5340","zip_code":"201"},
      {"id":"15","county_id":"2","name":"\u4e2d\u6b63\u5340","zip_code":"202"},
      {"id":"16","county_id":"2","name":"\u4e2d\u5c71\u5340","zip_code":"203"},
      {"id":"17","county_id":"2","name":"\u5b89\u6a02\u5340","zip_code":"204"},
      {"id":"18","county_id":"2","name":"\u6696\u6696\u5340","zip_code":"205"},
      {"id":"19","county_id":"2","name":"\u4e03\u5835\u5340","zip_code":"206"},
      {"id":"20","county_id":"3","name":"\u842c\u91cc\u5340","zip_code":"207"},
      {"id":"21","county_id":"3","name":"\u91d1\u5c71\u5340","zip_code":"208"},
      {"id":"22","county_id":"3","name":"\u677f\u6a4b\u5340","zip_code":"220"},
      {"id":"23","county_id":"3","name":"\u6c50\u6b62\u5340","zip_code":"221"},
      {"id":"24","county_id":"3","name":"\u6df1\u5751\u5340","zip_code":"222"},
      {"id":"25","county_id":"3","name":"\u77f3\u7887\u5340","zip_code":"223"},
      {"id":"26","county_id":"3","name":"\u745e\u82b3\u5340","zip_code":"224"},
      {"id":"27","county_id":"3","name":"\u5e73\u6eaa\u5340","zip_code":"226"},
      {"id":"28","county_id":"3","name":"\u96d9\u6eaa\u5340","zip_code":"227"},
      {"id":"29","county_id":"3","name":"\u8ca2\u5bee\u5340","zip_code":"228"},
      {"id":"30","county_id":"3","name":"\u65b0\u5e97\u5340","zip_code":"231"},
      {"id":"31","county_id":"3","name":"\u576a\u6797\u5340","zip_code":"232"},
      {"id":"32","county_id":"3","name":"\u70cf\u4f86\u5340","zip_code":"233"},
      {"id":"33","county_id":"3","name":"\u6c38\u548c\u5340","zip_code":"234"},
      {"id":"34","county_id":"3","name":"\u4e2d\u548c\u5340","zip_code":"235"},
      {"id":"35","county_id":"3","name":"\u571f\u57ce\u5340","zip_code":"236"},
      {"id":"36","county_id":"3","name":"\u4e09\u5cfd\u5340","zip_code":"237"},
      {"id":"37","county_id":"3","name":"\u6a39\u6797\u5340","zip_code":"238"},
      {"id":"38","county_id":"3","name":"\u9daf\u6b4c\u5340","zip_code":"239"},
      {"id":"39","county_id":"3","name":"\u4e09\u91cd\u5340","zip_code":"241"},
      {"id":"40","county_id":"3","name":"\u65b0\u838a\u5340","zip_code":"242"},
      {"id":"41","county_id":"3","name":"\u6cf0\u5c71\u5340","zip_code":"243"},
      {"id":"42","county_id":"3","name":"\u6797\u53e3\u5340","zip_code":"244"},
      {"id":"43","county_id":"3","name":"\u8606\u6d32\u5340","zip_code":"247"},
      {"id":"44","county_id":"3","name":"\u4e94\u80a1\u5340","zip_code":"248"},
      {"id":"45","county_id":"3","name":"\u516b\u91cc\u5340","zip_code":"249"},
      {"id":"46","county_id":"3","name":"\u6de1\u6c34\u5340","zip_code":"251"},
      {"id":"47","county_id":"3","name":"\u4e09\u829d\u5340","zip_code":"252"},
      {"id":"48","county_id":"3","name":"\u77f3\u9580\u5340","zip_code":"253"},
      {"id":"49","county_id":"4","name":"\u5b9c\u862d\u5e02","zip_code":"260"},
      {"id":"50","county_id":"4","name":"\u982d\u57ce\u93ae","zip_code":"261"},
      {"id":"51","county_id":"4","name":"\u7901\u6eaa\u9109","zip_code":"262"},
      {"id":"52","county_id":"4","name":"\u58ef\u570d\u9109","zip_code":"263"},
      {"id":"53","county_id":"4","name":"\u54e1\u5c71\u9109","zip_code":"264"},
      {"id":"54","county_id":"4","name":"\u7f85\u6771\u93ae","zip_code":"265"},
      {"id":"55","county_id":"4","name":"\u4e09\u661f\u9109","zip_code":"266"},
      {"id":"56","county_id":"4","name":"\u5927\u540c\u9109","zip_code":"267"},
      {"id":"57","county_id":"4","name":"\u4e94\u7d50\u9109","zip_code":"268"},
      {"id":"58","county_id":"4","name":"\u51ac\u5c71\u9109","zip_code":"269"},
      {"id":"59","county_id":"4","name":"\u8607\u6fb3\u93ae","zip_code":"270"},
      {"id":"60","county_id":"4","name":"\u5357\u6fb3\u9109","zip_code":"272"},
      {"id":"61","county_id":"5","name":"\u6771\u5340","zip_code":"300"},
      {"id":"62","county_id":"5","name":"\u5317\u5340","zip_code":"300"},
      {"id":"63","county_id":"5","name":"\u9999\u5c71\u5340","zip_code":"300"},
      {"id":"64","county_id":"6","name":"\u7af9\u5317\u5e02","zip_code":"302"},
      {"id":"65","county_id":"6","name":"\u6e56\u53e3\u9109","zip_code":"303"},
      {"id":"66","county_id":"6","name":"\u65b0\u8c50\u9109","zip_code":"304"},
      {"id":"67","county_id":"6","name":"\u65b0\u57d4\u93ae","zip_code":"305"},
      {"id":"68","county_id":"6","name":"\u95dc\u897f\u93ae","zip_code":"306"},
      {"id":"69","county_id":"6","name":"\u828e\u6797\u9109","zip_code":"307"},
      {"id":"70","county_id":"6","name":"\u5bf6\u5c71\u9109","zip_code":"308"},
      {"id":"71","county_id":"6","name":"\u7af9\u6771\u93ae","zip_code":"310"},
      {"id":"72","county_id":"6","name":"\u4e94\u5cf0\u9109","zip_code":"311"},
      {"id":"73","county_id":"6","name":"\u6a6b\u5c71\u9109","zip_code":"312"},
      {"id":"74","county_id":"6","name":"\u5c16\u77f3\u9109","zip_code":"313"},
      {"id":"75","county_id":"6","name":"\u5317\u57d4\u9109","zip_code":"314"},
      {"id":"76","county_id":"6","name":"\u5ce8\u7709\u9109","zip_code":"315"},
      {"id":"77","county_id":"7","name":"\u4e2d\u58e2\u5340","zip_code":"320"},
      {"id":"78","county_id":"7","name":"\u5e73\u93ae\u5340","zip_code":"324"},
      {"id":"79","county_id":"7","name":"\u9f8d\u6f6d\u5340","zip_code":"325"},
      {"id":"80","county_id":"7","name":"\u694a\u6885\u5340","zip_code":"326"},
      {"id":"81","county_id":"7","name":"\u65b0\u5c4b\u5340","zip_code":"327"},
      {"id":"82","county_id":"7","name":"\u89c0\u97f3\u5340","zip_code":"328"},
      {"id":"83","county_id":"7","name":"\u6843\u5712\u5340","zip_code":"330"},
      {"id":"84","county_id":"7","name":"\u9f9c\u5c71\u5340","zip_code":"333"},
      {"id":"85","county_id":"7","name":"\u516b\u5fb7\u5340","zip_code":"334"},
      {"id":"86","county_id":"7","name":"\u5927\u6eaa\u5340","zip_code":"335"},
      {"id":"87","county_id":"7","name":"\u5fa9\u8208\u5340","zip_code":"336"},
      {"id":"88","county_id":"7","name":"\u5927\u5712\u5340","zip_code":"337"},
      {"id":"89","county_id":"7","name":"\u8606\u7af9\u5340","zip_code":"338"},
      {"id":"90","county_id":"8","name":"\u7af9\u5357\u93ae","zip_code":"350"},
      {"id":"91","county_id":"8","name":"\u982d\u4efd\u93ae","zip_code":"351"},
      {"id":"92","county_id":"8","name":"\u4e09\u7063\u9109","zip_code":"352"},
      {"id":"93","county_id":"8","name":"\u5357\u5e84\u9109","zip_code":"353"},
      {"id":"94","county_id":"8","name":"\u7345\u6f6d\u9109","zip_code":"354"},
      {"id":"95","county_id":"8","name":"\u5f8c\u9f8d\u93ae","zip_code":"356"},
      {"id":"96","county_id":"8","name":"\u901a\u9704\u93ae","zip_code":"357"},
      {"id":"97","county_id":"8","name":"\u82d1\u88e1\u93ae","zip_code":"358"},
      {"id":"98","county_id":"8","name":"\u82d7\u6817\u5e02","zip_code":"360"},
      {"id":"99","county_id":"8","name":"\u9020\u6a4b\u9109","zip_code":"361"},
      {"id":"100","county_id":"8","name":"\u982d\u5c4b\u9109","zip_code":"362"},
      {"id":"101","county_id":"8","name":"\u516c\u9928\u9109","zip_code":"363"},
      {"id":"102","county_id":"8","name":"\u5927\u6e56\u9109","zip_code":"364"},
      {"id":"103","county_id":"8","name":"\u6cf0\u5b89\u9109","zip_code":"365"},
      {"id":"104","county_id":"8","name":"\u9285\u947c\u9109","zip_code":"366"},
      {"id":"105","county_id":"8","name":"\u4e09\u7fa9\u9109","zip_code":"367"},
      {"id":"106","county_id":"8","name":"\u897f\u6e56\u9109","zip_code":"368"},
      {"id":"107","county_id":"8","name":"\u5353\u862d\u93ae","zip_code":"369"},
      {"id":"108","county_id":"9","name":"\u4e2d\u5340","zip_code":"400"},
      {"id":"109","county_id":"9","name":"\u6771\u5340","zip_code":"401"},
      {"id":"110","county_id":"9","name":"\u5357\u5340","zip_code":"402"},
      {"id":"111","county_id":"9","name":"\u897f\u5340","zip_code":"403"},
      {"id":"112","county_id":"9","name":"\u5317\u5340","zip_code":"404"},
      {"id":"113","county_id":"9","name":"\u5317\u5c6f\u5340","zip_code":"406"},
      {"id":"114","county_id":"9","name":"\u897f\u5c6f\u5340","zip_code":"407"},
      {"id":"115","county_id":"9","name":"\u5357\u5c6f\u5340","zip_code":"408"},
      {"id":"116","county_id":"9","name":"\u592a\u5e73\u5340","zip_code":"411"},
      {"id":"117","county_id":"9","name":"\u5927\u91cc\u5340","zip_code":"412"},
      {"id":"118","county_id":"9","name":"\u9727\u5cf0\u5340","zip_code":"413"},
      {"id":"119","county_id":"9","name":"\u70cf\u65e5\u5340","zip_code":"414"},
      {"id":"120","county_id":"9","name":"\u8c50\u539f\u5340","zip_code":"420"},
      {"id":"121","county_id":"9","name":"\u540e\u91cc\u5340","zip_code":"421"},
      {"id":"122","county_id":"9","name":"\u77f3\u5ca1\u5340","zip_code":"422"},
      {"id":"123","county_id":"9","name":"\u6771\u52e2\u5340","zip_code":"423"},
      {"id":"124","county_id":"9","name":"\u548c\u5e73\u5340","zip_code":"424"},
      {"id":"125","county_id":"9","name":"\u65b0\u793e\u5340","zip_code":"426"},
      {"id":"126","county_id":"9","name":"\u6f6d\u5b50\u5340","zip_code":"427"},
      {"id":"127","county_id":"9","name":"\u5927\u96c5\u5340","zip_code":"428"},
      {"id":"128","county_id":"9","name":"\u795e\u5ca1\u5340","zip_code":"429"},
      {"id":"129","county_id":"9","name":"\u5927\u809a\u5340","zip_code":"432"},
      {"id":"130","county_id":"9","name":"\u6c99\u9e7f\u5340","zip_code":"433"},
      {"id":"131","county_id":"9","name":"\u9f8d\u4e95\u5340","zip_code":"434"},
      {"id":"132","county_id":"9","name":"\u68a7\u68f2\u5340","zip_code":"435"},
      {"id":"133","county_id":"9","name":"\u6e05\u6c34\u5340","zip_code":"436"},
      {"id":"134","county_id":"9","name":"\u5927\u7532\u5340","zip_code":"437"},
      {"id":"135","county_id":"9","name":"\u5916\u57d4\u5340","zip_code":"438"},
      {"id":"136","county_id":"9","name":"\u5927\u5b89\u5340","zip_code":"439"},
      {"id":"137","county_id":"10","name":"\u5f70\u5316\u5e02","zip_code":"500"},
      {"id":"138","county_id":"10","name":"\u82ac\u5712\u9109","zip_code":"502"},
      {"id":"139","county_id":"10","name":"\u82b1\u58c7\u9109","zip_code":"503"},
      {"id":"140","county_id":"10","name":"\u79c0\u6c34\u9109","zip_code":"504"},
      {"id":"141","county_id":"10","name":"\u9e7f\u6e2f\u93ae","zip_code":"505"},
      {"id":"142","county_id":"10","name":"\u798f\u8208\u9109","zip_code":"506"},
      {"id":"143","county_id":"10","name":"\u7dda\u897f\u9109","zip_code":"507"},
      {"id":"144","county_id":"10","name":"\u548c\u7f8e\u93ae","zip_code":"508"},
      {"id":"145","county_id":"10","name":"\u4f38\u6e2f\u9109","zip_code":"509"},
      {"id":"146","county_id":"10","name":"\u54e1\u6797\u93ae","zip_code":"510"},
      {"id":"147","county_id":"10","name":"\u793e\u982d\u9109","zip_code":"511"},
      {"id":"148","county_id":"10","name":"\u6c38\u9756\u9109","zip_code":"512"},
      {"id":"149","county_id":"10","name":"\u57d4\u5fc3\u9109","zip_code":"513"},
      {"id":"150","county_id":"10","name":"\u6eaa\u6e56\u93ae","zip_code":"514"},
      {"id":"151","county_id":"10","name":"\u5927\u6751\u9109","zip_code":"515"},
      {"id":"152","county_id":"10","name":"\u57d4\u9e7d\u9109","zip_code":"516"},
      {"id":"153","county_id":"10","name":"\u7530\u4e2d\u93ae","zip_code":"520"},
      {"id":"154","county_id":"10","name":"\u5317\u6597\u93ae","zip_code":"521"},
      {"id":"155","county_id":"10","name":"\u7530\u5c3e\u9109","zip_code":"522"},
      {"id":"156","county_id":"10","name":"\u57e4\u982d\u9109","zip_code":"523"},
      {"id":"157","county_id":"10","name":"\u6eaa\u5dde\u9109","zip_code":"524"},
      {"id":"158","county_id":"10","name":"\u7af9\u5858\u9109","zip_code":"525"},
      {"id":"159","county_id":"10","name":"\u4e8c\u6797\u93ae","zip_code":"526"},
      {"id":"160","county_id":"10","name":"\u5927\u57ce\u9109","zip_code":"527"},
      {"id":"161","county_id":"10","name":"\u82b3\u82d1\u9109","zip_code":"528"},
      {"id":"162","county_id":"10","name":"\u4e8c\u6c34\u9109","zip_code":"530"},
      {"id":"163","county_id":"11","name":"\u5357\u6295\u5e02","zip_code":"540"},
      {"id":"164","county_id":"11","name":"\u4e2d\u5bee\u9109","zip_code":"541"},
      {"id":"165","county_id":"11","name":"\u8349\u5c6f\u93ae","zip_code":"542"},
      {"id":"166","county_id":"11","name":"\u570b\u59d3\u9109","zip_code":"544"},
      {"id":"167","county_id":"11","name":"\u57d4\u91cc\u93ae","zip_code":"545"},
      {"id":"168","county_id":"11","name":"\u4ec1\u611b\u9109","zip_code":"546"},
      {"id":"169","county_id":"11","name":"\u540d\u9593\u9109","zip_code":"551"},
      {"id":"170","county_id":"11","name":"\u96c6\u96c6\u93ae","zip_code":"552"},
      {"id":"171","county_id":"11","name":"\u6c34\u91cc\u9109","zip_code":"553"},
      {"id":"172","county_id":"11","name":"\u9b5a\u6c60\u9109","zip_code":"555"},
      {"id":"173","county_id":"11","name":"\u4fe1\u7fa9\u9109","zip_code":"556"},
      {"id":"174","county_id":"11","name":"\u7af9\u5c71\u93ae","zip_code":"557"},
      {"id":"175","county_id":"11","name":"\u9e7f\u8c37\u9109","zip_code":"558"},
      {"id":"176","county_id":"12","name":"\u6771\u5340","zip_code":"600"},
      {"id":"177","county_id":"12","name":"\u897f\u5340","zip_code":"600"},
      {"id":"178","county_id":"13","name":"\u756a\u8def\u9109","zip_code":"602"},
      {"id":"179","county_id":"13","name":"\u6885\u5c71\u9109","zip_code":"603"},
      {"id":"180","county_id":"13","name":"\u7af9\u5d0e\u9109","zip_code":"604"},
      {"id":"181","county_id":"13","name":"\u963f\u91cc\u5c71","zip_code":"605"},
      {"id":"182","county_id":"13","name":"\u4e2d\u57d4\u9109","zip_code":"606"},
      {"id":"183","county_id":"13","name":"\u5927\u57d4\u9109","zip_code":"607"},
      {"id":"184","county_id":"13","name":"\u6c34\u4e0a\u9109","zip_code":"608"},
      {"id":"185","county_id":"13","name":"\u9e7f\u8349\u9109","zip_code":"611"},
      {"id":"186","county_id":"13","name":"\u592a\u4fdd\u5e02","zip_code":"612"},
      {"id":"187","county_id":"13","name":"\u6734\u5b50\u5e02","zip_code":"613"},
      {"id":"188","county_id":"13","name":"\u6771\u77f3\u9109","zip_code":"614"},
      {"id":"189","county_id":"13","name":"\u516d\u8173\u9109","zip_code":"615"},
      {"id":"190","county_id":"13","name":"\u65b0\u6e2f\u9109","zip_code":"616"},
      {"id":"191","county_id":"13","name":"\u6c11\u96c4\u9109","zip_code":"621"},
      {"id":"192","county_id":"13","name":"\u5927\u6797\u93ae","zip_code":"622"},
      {"id":"193","county_id":"13","name":"\u6eaa\u53e3\u9109","zip_code":"623"},
      {"id":"194","county_id":"13","name":"\u7fa9\u7af9\u9109","zip_code":"624"},
      {"id":"195","county_id":"13","name":"\u5e03\u888b\u93ae","zip_code":"625"},
      {"id":"196","county_id":"14","name":"\u6597\u5357\u93ae","zip_code":"630"},
      {"id":"197","county_id":"14","name":"\u5927\u57e4\u9109","zip_code":"631"},
      {"id":"198","county_id":"14","name":"\u864e\u5c3e\u93ae","zip_code":"632"},
      {"id":"199","county_id":"14","name":"\u571f\u5eab\u93ae","zip_code":"633"},
      {"id":"200","county_id":"14","name":"\u8912\u5fe0\u9109","zip_code":"634"},
      {"id":"201","county_id":"14","name":"\u6771\u52e2\u9109","zip_code":"635"},
      {"id":"202","county_id":"14","name":"\u53f0\u897f\u9109","zip_code":"636"},
      {"id":"203","county_id":"14","name":"\u5d19\u80cc\u9109","zip_code":"637"},
      {"id":"204","county_id":"14","name":"\u9ea5\u5bee\u9109","zip_code":"638"},
      {"id":"205","county_id":"14","name":"\u6597\u516d\u5e02","zip_code":"640"},
      {"id":"206","county_id":"14","name":"\u6797\u5167\u9109","zip_code":"643"},
      {"id":"207","county_id":"14","name":"\u53e4\u5751\u9109","zip_code":"646"},
      {"id":"208","county_id":"14","name":"\u83bf\u6850\u9109","zip_code":"647"},
      {"id":"209","county_id":"14","name":"\u897f\u87ba\u93ae","zip_code":"648"},
      {"id":"210","county_id":"14","name":"\u4e8c\u5d19\u9109","zip_code":"649"},
      {"id":"211","county_id":"14","name":"\u5317\u6e2f\u93ae","zip_code":"651"},
      {"id":"212","county_id":"14","name":"\u6c34\u6797\u9109","zip_code":"652"},
      {"id":"213","county_id":"14","name":"\u53e3\u6e56\u9109","zip_code":"653"},
      {"id":"214","county_id":"14","name":"\u56db\u6e56\u9109","zip_code":"654"},
      {"id":"215","county_id":"14","name":"\u5143\u9577\u9109","zip_code":"655"},
      {"id":"216","county_id":"15","name":"\u4e2d\u897f\u5340","zip_code":"700"},
      {"id":"217","county_id":"15","name":"\u6771\u5340","zip_code":"701"},
      {"id":"218","county_id":"15","name":"\u5357\u5340","zip_code":"702"},
      {"id":"219","county_id":"15","name":"\u5317\u5340","zip_code":"704"},
      {"id":"220","county_id":"15","name":"\u5b89\u5e73\u5340","zip_code":"708"},
      {"id":"221","county_id":"15","name":"\u5b89\u5357\u5340","zip_code":"709"},
      {"id":"222","county_id":"15","name":"\u6c38\u5eb7\u5340","zip_code":"710"},
      {"id":"223","county_id":"15","name":"\u6b78\u4ec1\u5340","zip_code":"711"},
      {"id":"224","county_id":"15","name":"\u65b0\u5316\u5340","zip_code":"712"},
      {"id":"225","county_id":"15","name":"\u5de6\u93ae\u5340","zip_code":"713"},
      {"id":"226","county_id":"15","name":"\u7389\u4e95\u5340","zip_code":"714"},
      {"id":"227","county_id":"15","name":"\u6960\u897f\u5340","zip_code":"715"},
      {"id":"228","county_id":"15","name":"\u5357\u5316\u5340","zip_code":"716"},
      {"id":"229","county_id":"15","name":"\u4ec1\u5fb7\u5340","zip_code":"717"},
      {"id":"230","county_id":"15","name":"\u95dc\u5edf\u5340","zip_code":"718"},
      {"id":"231","county_id":"15","name":"\u9f8d\u5d0e\u5340","zip_code":"719"},
      {"id":"232","county_id":"15","name":"\u5b98\u7530\u5340","zip_code":"720"},
      {"id":"233","county_id":"15","name":"\u9ebb\u8c46\u5340","zip_code":"721"},
      {"id":"234","county_id":"15","name":"\u4f73\u91cc\u5340","zip_code":"722"},
      {"id":"235","county_id":"15","name":"\u897f\u6e2f\u5340","zip_code":"723"},
      {"id":"236","county_id":"15","name":"\u4e03\u80a1\u5340","zip_code":"724"},
      {"id":"237","county_id":"15","name":"\u5c07\u8ecd\u5340","zip_code":"725"},
      {"id":"238","county_id":"15","name":"\u5b78\u7532\u5340","zip_code":"726"},
      {"id":"239","county_id":"15","name":"\u5317\u9580\u5340","zip_code":"727"},
      {"id":"240","county_id":"15","name":"\u65b0\u71df\u5340","zip_code":"730"},
      {"id":"241","county_id":"15","name":"\u5f8c\u58c1\u5340","zip_code":"731"},
      {"id":"242","county_id":"15","name":"\u767d\u6cb3\u5340","zip_code":"732"},
      {"id":"243","county_id":"15","name":"\u6771\u5c71\u5340","zip_code":"733"},
      {"id":"244","county_id":"15","name":"\u516d\u7532\u5340","zip_code":"734"},
      {"id":"245","county_id":"15","name":"\u4e0b\u71df\u5340","zip_code":"735"},
      {"id":"246","county_id":"15","name":"\u67f3\u71df\u5340","zip_code":"736"},
      {"id":"247","county_id":"15","name":"\u9e7d\u6c34\u5340","zip_code":"737"},
      {"id":"248","county_id":"15","name":"\u5584\u5316\u5340","zip_code":"741"},
      {"id":"249","county_id":"15","name":"\u5927\u5167\u5340","zip_code":"742"},
      {"id":"250","county_id":"15","name":"\u5c71\u4e0a\u5340","zip_code":"743"},
      {"id":"251","county_id":"15","name":"\u65b0\u5e02\u5340","zip_code":"744"},
      {"id":"252","county_id":"15","name":"\u5b89\u5b9a\u5340","zip_code":"745"},
      {"id":"253","county_id":"16","name":"\u65b0\u8208\u5340","zip_code":"800"},
      {"id":"254","county_id":"16","name":"\u524d\u91d1\u5340","zip_code":"801"},
      {"id":"255","county_id":"16","name":"\u82d3\u96c5\u5340","zip_code":"802"},
      {"id":"256","county_id":"16","name":"\u9e7d\u57d5\u5340","zip_code":"803"},
      {"id":"257","county_id":"16","name":"\u9f13\u5c71\u5340","zip_code":"804"},
      {"id":"258","county_id":"16","name":"\u65d7\u6d25\u5340","zip_code":"805"},
      {"id":"259","county_id":"16","name":"\u524d\u93ae\u5340","zip_code":"806"},
      {"id":"260","county_id":"16","name":"\u4e09\u6c11\u5340","zip_code":"807"},
      {"id":"261","county_id":"16","name":"\u6960\u6893\u5340","zip_code":"811"},
      {"id":"262","county_id":"16","name":"\u5c0f\u6e2f\u5340","zip_code":"812"},
      {"id":"263","county_id":"16","name":"\u5de6\u71df\u5340","zip_code":"813"},
      {"id":"264","county_id":"16","name":"\u4ec1\u6b66\u5340","zip_code":"814"},
      {"id":"265","county_id":"16","name":"\u5927\u793e\u5340","zip_code":"815"},
      {"id":"266","county_id":"16","name":"\u5ca1\u5c71\u5340","zip_code":"820"},
      {"id":"267","county_id":"16","name":"\u8def\u7af9\u5340","zip_code":"821"},
      {"id":"268","county_id":"16","name":"\u963f\u84ee\u5340","zip_code":"822"},
      {"id":"269","county_id":"16","name":"\u7530\u5bee\u5340","zip_code":"823"},
      {"id":"270","county_id":"16","name":"\u71d5\u5de2\u5340","zip_code":"824"},
      {"id":"271","county_id":"16","name":"\u6a4b\u982d\u5340","zip_code":"825"},
      {"id":"272","county_id":"16","name":"\u6893\u5b98\u5340","zip_code":"826"},
      {"id":"273","county_id":"16","name":"\u5f4c\u9640\u5340","zip_code":"827"},
      {"id":"274","county_id":"16","name":"\u6c38\u5b89\u5340","zip_code":"828"},
      {"id":"275","county_id":"16","name":"\u6e56\u5167\u5340","zip_code":"829"},
      {"id":"276","county_id":"16","name":"\u9cf3\u5c71\u5340","zip_code":"830"},
      {"id":"277","county_id":"16","name":"\u5927\u5bee\u5340","zip_code":"831"},
      {"id":"278","county_id":"16","name":"\u6797\u5712\u5340","zip_code":"832"},
      {"id":"279","county_id":"16","name":"\u9ce5\u677e\u5340","zip_code":"833"},
      {"id":"280","county_id":"16","name":"\u5927\u6a39\u5340","zip_code":"840"},
      {"id":"281","county_id":"16","name":"\u65d7\u5c71\u5340","zip_code":"842"},
      {"id":"282","county_id":"16","name":"\u7f8e\u6fc3\u5340","zip_code":"843"},
      {"id":"283","county_id":"16","name":"\u516d\u9f9c\u5340","zip_code":"844"},
      {"id":"284","county_id":"16","name":"\u5167\u9580\u5340","zip_code":"845"},
      {"id":"285","county_id":"16","name":"\u6749\u6797\u5340","zip_code":"846"},
      {"id":"286","county_id":"16","name":"\u7532\u4ed9\u5340","zip_code":"847"},
      {"id":"287","county_id":"16","name":"\u6843\u6e90\u5340","zip_code":"848"},
      {"id":"288","county_id":"16","name":"\u90a3\u746a\u590f\u5340","zip_code":"849"},
      {"id":"289","county_id":"16","name":"\u8302\u6797\u5340","zip_code":"851"},
      {"id":"290","county_id":"16","name":"\u8304\u8423\u5340","zip_code":"852"},
      {"id":"291","county_id":"17","name":"\u99ac\u516c\u5e02","zip_code":"880"},
      {"id":"292","county_id":"17","name":"\u897f\u5dbc\u9109","zip_code":"881"},
      {"id":"293","county_id":"17","name":"\u671b\u5b89\u9109","zip_code":"882"},
      {"id":"294","county_id":"17","name":"\u4e03\u7f8e\u9109","zip_code":"883"},
      {"id":"295","county_id":"17","name":"\u767d\u6c99\u9109","zip_code":"884"},
      {"id":"296","county_id":"17","name":"\u6e56\u897f\u9109","zip_code":"885"},
      {"id":"297","county_id":"18","name":"\u5c4f\u6771\u5e02","zip_code":"900"},
      {"id":"298","county_id":"18","name":"\u4e09\u5730\u9580\u9109","zip_code":"901"},
      {"id":"299","county_id":"18","name":"\u9727\u53f0\u9109","zip_code":"902"},
      {"id":"300","county_id":"18","name":"\u746a\u5bb6\u9109","zip_code":"903"},
      {"id":"301","county_id":"18","name":"\u4e5d\u5982\u9109","zip_code":"904"},
      {"id":"302","county_id":"18","name":"\u91cc\u6e2f\u9109","zip_code":"905"},
      {"id":"303","county_id":"18","name":"\u9ad8\u6a39\u9109","zip_code":"906"},
      {"id":"304","county_id":"18","name":"\u9e7d\u57d4\u9109","zip_code":"907"},
      {"id":"305","county_id":"18","name":"\u9577\u6cbb\u9109","zip_code":"908"},
      {"id":"306","county_id":"18","name":"\u9e9f\u6d1b\u9109","zip_code":"909"},
      {"id":"307","county_id":"18","name":"\u7af9\u7530\u9109","zip_code":"911"},
      {"id":"308","county_id":"18","name":"\u5167\u57d4\u9109","zip_code":"912"},
      {"id":"309","county_id":"18","name":"\u842c\u4e39\u9109","zip_code":"913"},
      {"id":"310","county_id":"18","name":"\u6f6e\u5dde\u93ae","zip_code":"920"},
      {"id":"311","county_id":"18","name":"\u6cf0\u6b66\u9109","zip_code":"921"},
      {"id":"312","county_id":"18","name":"\u4f86\u7fa9\u9109","zip_code":"922"},
      {"id":"313","county_id":"18","name":"\u842c\u5dd2\u9109","zip_code":"923"},
      {"id":"314","county_id":"18","name":"\u5d01\u9802\u9109","zip_code":"924"},
      {"id":"315","county_id":"18","name":"\u65b0\u57e4\u9109","zip_code":"925"},
      {"id":"316","county_id":"18","name":"\u5357\u5dde\u9109","zip_code":"926"},
      {"id":"317","county_id":"18","name":"\u6797\u908a\u9109","zip_code":"927"},
      {"id":"318","county_id":"18","name":"\u6771\u6e2f\u93ae","zip_code":"928"},
      {"id":"319","county_id":"18","name":"\u7409\u7403\u9109","zip_code":"929"},
      {"id":"320","county_id":"18","name":"\u4f73\u51ac\u9109","zip_code":"931"},
      {"id":"321","county_id":"18","name":"\u65b0\u5712\u9109","zip_code":"932"},
      {"id":"322","county_id":"18","name":"\u678b\u5bee\u9109","zip_code":"940"},
      {"id":"323","county_id":"18","name":"\u678b\u5c71\u9109","zip_code":"941"},
      {"id":"324","county_id":"18","name":"\u6625\u65e5\u9109","zip_code":"942"},
      {"id":"325","county_id":"18","name":"\u7345\u5b50\u9109","zip_code":"943"},
      {"id":"326","county_id":"18","name":"\u8eca\u57ce\u9109","zip_code":"944"},
      {"id":"327","county_id":"18","name":"\u7261\u4e39\u9109","zip_code":"945"},
      {"id":"328","county_id":"18","name":"\u6046\u6625\u93ae","zip_code":"946"},
      {"id":"329","county_id":"18","name":"\u6eff\u5dde\u9109","zip_code":"947"},
      {"id":"330","county_id":"19","name":"\u53f0\u6771\u5e02","zip_code":"950"},
      {"id":"331","county_id":"19","name":"\u7da0\u5cf6\u9109","zip_code":"951"},
      {"id":"332","county_id":"19","name":"\u862d\u5dbc\u9109","zip_code":"952"},
      {"id":"333","county_id":"19","name":"\u5ef6\u5e73\u9109","zip_code":"953"},
      {"id":"334","county_id":"19","name":"\u5351\u5357\u9109","zip_code":"954"},
      {"id":"335","county_id":"19","name":"\u9e7f\u91ce\u9109","zip_code":"955"},
      {"id":"336","county_id":"19","name":"\u95dc\u5c71\u93ae","zip_code":"956"},
      {"id":"337","county_id":"19","name":"\u6d77\u7aef\u9109","zip_code":"957"},
      {"id":"338","county_id":"19","name":"\u6c60\u4e0a\u9109","zip_code":"958"},
      {"id":"339","county_id":"19","name":"\u6771\u6cb3\u9109","zip_code":"959"},
      {"id":"340","county_id":"19","name":"\u6210\u529f\u93ae","zip_code":"961"},
      {"id":"341","county_id":"19","name":"\u9577\u6ff1\u9109","zip_code":"962"},
      {"id":"342","county_id":"19","name":"\u592a\u9ebb\u91cc","zip_code":"963"},
      {"id":"343","county_id":"19","name":"\u91d1\u5cf0\u9109","zip_code":"964"},
      {"id":"344","county_id":"19","name":"\u5927\u6b66\u9109","zip_code":"965"},
      {"id":"345","county_id":"19","name":"\u9054\u4ec1\u9109","zip_code":"966"},
      {"id":"346","county_id":"20","name":"\u82b1\u84ee\u5e02","zip_code":"970"},
      {"id":"347","county_id":"20","name":"\u65b0\u57ce\u9109","zip_code":"971"},
      {"id":"348","county_id":"20","name":"\u79c0\u6797\u9109","zip_code":"972"},
      {"id":"349","county_id":"20","name":"\u5409\u5b89\u9109","zip_code":"973"},
      {"id":"350","county_id":"20","name":"\u58fd\u8c50\u9109","zip_code":"974"},
      {"id":"351","county_id":"20","name":"\u9cf3\u6797\u93ae","zip_code":"975"},
      {"id":"352","county_id":"20","name":"\u5149\u5fa9\u9109","zip_code":"976"},
      {"id":"353","county_id":"20","name":"\u8c50\u6ff1\u9109","zip_code":"977"},
      {"id":"354","county_id":"20","name":"\u745e\u7a57\u9109","zip_code":"978"},
      {"id":"355","county_id":"20","name":"\u842c\u69ae\u9109","zip_code":"979"},
      {"id":"356","county_id":"20","name":"\u7389\u91cc\u93ae","zip_code":"981"},
      {"id":"357","county_id":"20","name":"\u5353\u6eaa\u9109","zip_code":"982"},
      {"id":"358","county_id":"20","name":"\u5bcc\u91cc\u9109","zip_code":"983"},
      {"id":"359","county_id":"21","name":"\u91d1\u6c99","zip_code":"890"},
      {"id":"360","county_id":"21","name":"\u91d1\u6e56\u93ae","zip_code":"891"},
      {"id":"361","county_id":"21","name":"\u91d1\u5be7\u9109","zip_code":"892"},
      {"id":"362","county_id":"21","name":"\u91d1\u57ce\u93ae","zip_code":"893"},
      {"id":"363","county_id":"21","name":"\u70c8\u5dbc\u9109","zip_code":"894"},
      {"id":"364","county_id":"21","name":"\u70cf\u5775\u9109","zip_code":"896"},
      {"id":"365","county_id":"22","name":"\u5357\u7aff\u9109","zip_code":"209"},
      {"id":"366","county_id":"22","name":"\u5317\u7aff\u9109","zip_code":"210"},
      {"id":"367","county_id":"22","name":"\u8392\u5149\u9109","zip_code":"211"},
      {"id":"368","county_id":"22","name":"\u6771\u5f15\u9109","zip_code":"212"},
      {"id":"369","county_id":"23","name":"\u6771\u6c99","zip_code":"817"},
      {"id":"370","county_id":"23","name":"\u5357\u6c99","zip_code":"819"}
    ]
  }
]
